Workbook
Name Slicer_Currently_residing_in_which_Regional_Council?: #N/A

Sheet National Pivot
A1: Last Year Enrollment | B1: (All)
H2: Specialization | I2: (blank)
A3: Row Labels | B3: Total Enrollment | C3: Sum of Count for Candiodates started course | D3: Sum of One verses Program Registered
A4: Southern | B4: 585 | C4: 501 | D4: 840 | H4: Row Labels | I4: Count of Unique Id
A5: Central | B5: 396 | C5: 301 | D5: 448 | H5: Central | I5: 95
A6: Gilgit | B6: 245 | C6: 173 | D6: 235 | H6: Southern | I6: 84
A7: Lower Chitral | B7: 112 | C7: 77 | D7: 127 | H7: Gilgit | I7: 72
A8: Hunza | B8: 111 | C8: 76 | D8: 107 | H8: Lower Chitral | I8: 35
A9: Ishkoman Puniyal | B9: 84 | C9: 64 | D9: 86 | H9: Hunza | I9: 35
A10: Upper Chitral | B10: 74 | C10: 55 | D10: 84 | H10: National | I10: 34
A11: Gupis Yasin | B11: 72 | C11: 60 | D11: 85 | H11: Ishkoman Puniyal | I11: 20
A12: National | B12: 53 | C12: 19 | D12: 26 | H12: Upper Chitral | I12: 19
A13: (blank) | H13: Gupis Yasin | I13: 12
A14: Grand Total | B14: 1732 | C14: 1326 | D14: 2038 | H14: (blank)
H15: Grand Total | I15: 406
G30: Completed | H30: No | K30: Completed | L30: No | O30: Completed | P30: No
A31: Completion % | B31: 1 | G31: Completion % | H31: (Multiple Items) | K31: Completion % | L31: 0 | O31: Completion % | P31: (Multiple Items)
A33: Row Labels | B33: Total Enrollment | C33: Count of Count for Yes | G33: Row Labels | H33: Total Enrollment | I33: Count of Specialization | K33: Row Labels | L33: Total Enrollment | M33: Count of Specialization | O33: Row Labels | P33: Total Enrollment | Q33: Count of Specialization
A34: Southern | B34: 134 | C34: 211 | G34: Southern | H34: 128 | I34: 232 | K34: Southern | L34: 200 | M34: 336 | O34: Southern | P34: 39 | Q34: 61
A35: Central | B35: 42 | C35: 47 | G35: Central | H35: 97 | I35: 144 | K35: Central | L35: 151 | M35: 242 | O35: Central | P35: 11 | Q35: 15
A36: Gilgit | B36: 26 | C36: 30 | G36: Gilgit | H36: 54 | I36: 77 | K36: Gilgit | L36: 87 | M36: 118 | O36: Gilgit | P36: 6 | Q36: 10
A37: Lower Chitral | B37: 13 | C37: 16 | G37: Hunza | H37: 29 | I37: 40 | K37: Ishkoman Puniyal | L37: 43 | M37: 58 | O37: Lower Chitral | P37: 6 | Q37: 10
A38: Hunza | B38: 10 | C38: 11 | G38: Lower Chitral | H38: 28 | I38: 44 | K38: Hunza | L38: 32 | M38: 49 | O38: Hunza | P38: 5 | Q38: 7
A39: Gupis Yasin | B39: 9 | C39: 10 | G39: Gupis Yasin | H39: 23 | I39: 29 | K39: Lower Chitral | L39: 30 | M39: 57 | O39: Gupis Yasin | P39: 4 | Q39: 9
A40: Upper Chitral | B40: 8 | C40: 10 | G40: Upper Chitral | H40: 17 | I40: 28 | K40: Upper Chitral | L40: 28 | M40: 44 | O40: Ishkoman Puniyal | P40: 3 | Q40: 3
A41: Ishkoman Puniyal | B41: 4 | C41: 5 | G41: Ishkoman Puniyal | H41: 14 | I41: 20 | K41: Gupis Yasin | L41: 24 | M41: 37 | O41: National | P41: 2 | Q41: 2
A42: National | B42: 1 | C42: 1 | G42: National | H42: 6 | I42: 8 | K42: National | L42: 10 | M42: 15 | O42: Upper Chitral | P42: 2 | Q42: 2
A43: Grand Total | B43: 247 | C43: 341 | G43: Grand Total | H43: 396 | I43: 622 | K43: Grand Total | L43: 605 | M43: 956 | O43: Grand Total | P43: 78 | Q43: 119
A52: Row Labels | B52: Total Candidates | C52: Course Started | D52: Course not Started
A53: Student | B53: 599 | C53: 474 | D53: 125
A54: Employed | B54: 470 | C54: 391 | D54: 79
A55: Unemployed | B55: 337 | C55: 263 | D55: 74
A56: Fresh Graduate | B56: 118 | C56: 92 | D56: 26
A57: Data not available | B57: 114 | C57: 33 | D57: 81
A58: Self Employed | B58: 64 | C58: 52 | D58: 12
A59: Entrepreneur | B59: 30 | C59: 21 | D59: 9
A60: (blank) | D60: 0
A61: Grand Total | B61: 1732 | C61: 1326 | D61: 406
A65: Row Labels | B65: Course Started | C65: Course Not started
A66: Below 25,000 | B66: 102 | C66: 33
A67: 25,000 - 50,000 | B67: 357 | C67: 121
A68: 60,000 - 80,000 | B68: 289 | C68: 68
A69: 80,001 - 100,000 | B69: 177 | C69: 48
A70: 100,001 - 120,000 | B70: 124 | C70: 23
A71: 140,000 - 160,000 | B71: 68 | C71: 10
A72: 180,000 - 200,000 | B72: 80 | C72: 5
A73: 200,000 above | B73: 96 | C73: 17
A74: Data not available | B74: 33 | C74: 81
A75: (blank) | C75: 0
A76: Grand Total | B76: 1326 | C76: 406
A86: No. of Course | B86: Total Candidates | C86: Total Courses Completed
A87: 1 | B87: 869 | C87: 54
A88: 2 | B88: 318 | C88: 129
A89: 3 | B89: 92 | C89: 84
A90: 4 | B90: 24 | C90: 27
A91: 5 | B91: 9 | C91: 5
A92: 6 | B92: 6 | C92: 17
A93: 8 | B93: 1 | C93: 0
A94: 9 | B94: 2 | C94: 8
A95: 10 | B95: 1 | C95: 2
A96: 11 | B96: 4 | C96: 15
A97: Grand Total | B97: 1326 | C97: 341
A102: Completion % | B102: 1
A104: No. of Course | B104: Total Candidates
A105: Google IT Automation with Python | B105: 4
A106: Google Advanced Data Analytics | B106: 7
A107: Google Cybersecurity | B107: 11
A108: Google Business Intelligence | B108: 12
A109: Google UX Design | B109: 12
A110: Google IT Support | B110: 12
A111: Google Data Analytics | B111: 21
A112: Google Project Management | B112: 29
A113: Google Digital Marketing & E-commerce | B113: 30
A114: Google Prompting Essentials | B114: 56
A115: Google AI Essentials | B115: 146
A116: Grand Total | B116: 340
A120: Row Labels | B120: Sum of Count for Enrollment | C120: Course Started | D120: Course Not started
A121: Female | B121: 700 | C121: 548 | D121: 152
A122: Male | B122: 918 | C122: 745 | D122: 173
A123: Not available in Google Form Data | B123: 114 | C123: 33 | D123: 81
A124: (blank) | D124: 0
A125: Grand Total | B125: 1732 | C125: 1326 | D125: 406
A136: Count of Name | B136: Column Labels
A137: No. of Course | B137: Incomplete | C137: Completed | D137: Grand total
A138: Google Data Analytics | B138: 385 | C138: 21 | D138: =GETPIVOTDATA("Name",$A$136,"Specialization",A138,"Completed","Incomplete")+GETPIVOTDATA("Name",$A$136,"Specialization",A138,"Completed","Completed") -> 406
A139: Google Digital Marketing & E-commerce | B139: 324 | C139: 30 | D139: =GETPIVOTDATA("Name",$A$136,"Specialization",A139,"Completed","Incomplete")+GETPIVOTDATA("Name",$A$136,"Specialization",A139,"Completed","Completed") -> 354
A140: Google Project Management | B140: 283 | C140: 29 | D140: =GETPIVOTDATA("Name",$A$136,"Specialization",A140,"Completed","Incomplete")+GETPIVOTDATA("Name",$A$136,"Specialization",A140,"Completed","Completed") -> 312
A141: Google Cybersecurity | B141: 147 | C141: 11 | D141: =GETPIVOTDATA("Name",$A$136,"Specialization",A141,"Completed","Incomplete")+GETPIVOTDATA("Name",$A$136,"Specialization",A141,"Completed","Completed") -> 158
A142: Google AI Essentials | B142: 136 | C142: 146 | D142: =GETPIVOTDATA("Name",$A$136,"Specialization",A142,"Completed","Incomplete")+GETPIVOTDATA("Name",$A$136,"Specialization",A142,"Completed","Completed") -> 282
A143: Google Advanced Data Analytics | B143: 89 | C143: 7 | D143: =GETPIVOTDATA("Name",$A$136,"Specialization",A143,"Completed","Incomplete")+GETPIVOTDATA("Name",$A$136,"Specialization",A143,"Completed","Completed") -> 96
A144: Google IT Support | B144: 79 | C144: 12 | D144: =GETPIVOTDATA("Name",$A$136,"Specialization",A144,"Completed","Incomplete")+GETPIVOTDATA("Name",$A$136,"Specialization",A144,"Completed","Completed") -> 91
A145: Google Prompting Essentials | B145: 77 | C145: 56 | D145: =GETPIVOTDATA("Name",$A$136,"Specialization",A145,"Completed","Incomplete")+GETPIVOTDATA("Name",$A$136,"Specialization",A145,"Completed","Completed") -> 133
A146: Google UX Design | B146: 69 | C146: 12 | D146: =GETPIVOTDATA("Name",$A$136,"Specialization",A146,"Completed","Incomplete")+GETPIVOTDATA("Name",$A$136,"Specialization",A146,"Completed","Completed") -> 81
A147: Google IT Automation with Python | B147: 55 | C147: 4 | D147: =GETPIVOTDATA("Name",$A$136,"Specialization",A147,"Completed","Incomplete")+GETPIVOTDATA("Name",$A$136,"Specialization",A147,"Completed","Completed") -> 59
A148: Google Business Intelligence | B148: 45 | C148: 12 | D148: =GETPIVOTDATA("Name",$A$136,"Specialization",A148,"Completed","Incomplete")+GETPIVOTDATA("Name",$A$136,"Specialization",A148,"Completed","Completed") -> 57
A149: Google Marketing Digital e E-Commerce | B149: 4 | D149: =GETPIVOTDATA("Name",$A$136,"Specialization",A149,"Completed","Incomplete")+GETPIVOTDATA("Name",$A$136,"Specialization",A149,"Completed","Completed") -> 4
A150: Google Data Analysis with Python | B150: 1 | D150: =GETPIVOTDATA("Name",$A$136,"Specialization",A150,"Completed","Incomplete")+GETPIVOTDATA("Name",$A$136,"Specialization",A150,"Completed","Completed") -> 1
A151: Google Digital Customer Engagement | B151: 1 | D151: =GETPIVOTDATA("Name",$A$136,"Specialization",A151,"Completed","Incomplete")+GETPIVOTDATA("Name",$A$136,"Specialization",A151,"Completed","Completed") -> 1
A152: Marketing digital e e-commerce do Google | B152: 1 | D152: =GETPIVOTDATA("Name",$A$136,"Specialization",A152,"Completed","Incomplete")+GETPIVOTDATA("Name",$A$136,"Specialization",A152,"Completed","Completed") -> 1
A153: Google Data Analytics (PT) | B153: 1 | D153: =GETPIVOTDATA("Name",$A$136,"Specialization",A153,"Completed","Incomplete")+GETPIVOTDATA("Name",$A$136,"Specialization",A153,"Completed","Completed") -> 1
...

Sheet Regions Pivot
A1: Currently residing in which Regional Council? | B1: Southern (Karachi / Interior Sindh) | I1: Currently residing in which Regional Council? | J1: Southern (Karachi / Interior Sindh) | P1: =B1 -> Southern (Karachi / Interior Sindh)
I2: Specialization | J2: (blank)
A3: Row Labels | B3: Sum of Count for Enrollment | C3: Sum of Count for Candiodates started course | D3: Count of Specialization
A4: Karimabad_Southern Region | B4: 149 | C4: 135 | D4: 237 | I4: Row Labels | J4: Count of Unique Id
A5: Garden_Southern Region | B5: 141 | C5: 114 | D5: 187 | I5: Garden_Southern Region | J5: 27
A6: Gulshan_Southern Region | B6: 139 | C6: 128 | D6: 235 | I6: Gulshan_Southern Region | J6: 11
A7: Hyderabad_Southern Region | B7: 50 | C7: 39 | D7: 63 | I7: Hyderabad_Southern Region | J7: 11
A8: Kharadar_Southern Region | B8: 42 | C8: 35 | D8: 50 | I8: Karimabad_Southern Region | J8: 14
A9: Thatta & Shah Bunder_Southern Region | B9: 30 | C9: 27 | D9: 38 | I9: Kharadar_Southern Region | J9: 7
A10: Tando Turel_Southern Region | B10: 21 | C10: 18 | D10: 25 | I10: Not available in Google Form Data | J10: 8
A11: Not available in Google Form Data | B11: 13 | C11: 5 | D11: 5 | I11: Tando Turel_Southern Region | J11: 3
A12: Grand Total | B12: 585 | C12: 501 | D12: 840 | I12: Thatta & Shah Bunder_Southern Region | J12: 3
I13: Grand Total | J13: 84
A26: Currently residing in which Regional Council? | B26: Southern (Karachi / Interior Sindh) | E26: Currently residing in which Regional Council? | F26: Southern (Karachi / Interior Sindh) | J26: Currently residing in which Regional Council? | K26: Southern (Karachi / Interior Sindh) | P26: Currently residing in which Regional Council? | Q26: Southern (Karachi / Interior Sindh)
A27: Completion % | B27: 1 | E27: Completion % | F27: (Multiple Items) | J27: Completion % | K27: (Multiple Items) | P27: Completion % | Q27: (Multiple Items)
A29: Row Labels | B29: Candidates | C29: Courses Completed | E29: Row Labels | F29: Candidates | G29: Courses Completed | J29: Row Labels | K29: Candidates | L29: Courses Completed | P29: Row Labels | Q29: Candidates | R29: Courses Completed
A30: Gulshan_Southern Region | B30: 43 | C30: 75 | E30: Gulshan_Southern Region | F30: 13 | G30: 26 | J30: Karimabad_Southern Region | K30: 35 | L30: 74 | P30: Karimabad_Southern Region | Q30: 55 | R30: 93
A31: Karimabad_Southern Region | B31: 34 | C31: 54 | E31: Karimabad_Southern Region | F31: 11 | G31: 16 | J31: Gulshan_Southern Region | K31: 34 | L31: 62 | P31: Garden_Southern Region | Q31: 49 | R31: 89
A32: Garden_Southern Region | B32: 32 | C32: 45 | E32: Garden_Southern Region | F32: 7 | G32: 9 | J32: Garden_Southern Region | K32: 28 | L32: 46 | P32: Gulshan_Southern Region | Q32: 38 | R32: 72
A33: Thatta & Shah Bunder_Southern Region | B33: 10 | C33: 13 | E33: Thatta & Shah Bunder_Southern Region | F33: 2 | G33: 2 | J33: Hyderabad_Southern Region | K33: 11 | L33: 22 | P33: Hyderabad_Southern Region | Q33: 19 | R33: 26
A34: Hyderabad_Southern Region | B34: 7 | C34: 12 | E34: Tando Turel_Southern Region | F34: 2 | G34: 2 | J34: Kharadar_Southern Region | K34: 8 | L34: 11 | P34: Kharadar_Southern Region | Q34: 19 | R34: 28
A35: Kharadar_Southern Region | B35: 6 | C35: 8 | E35: Hyderabad_Southern Region | F35: 2 | G35: 3 | J35: Tando Turel_Southern Region | K35: 6 | L35: 7 | P35: Thatta & Shah Bunder_Southern Region | Q35: 10 | R35: 14
A36: Tando Turel_Southern Region | B36: 2 | C36: 4 | E36: Kharadar_Southern Region | F36: 2 | G36: 3 | J36: Thatta & Shah Bunder_Southern Region | K36: 5 | L36: 9 | P36: Tando Turel_Southern Region | Q36: 8 | R36: 12
A37: Grand Total | B37: 134 | C37: 211 | E37: Grand Total | F37: 39 | G37: 61 | J37: Not available in Google Form Data | K37: 2 | L37: 2 | P37: Not available in Google Form Data | Q37: 3 | R37: 3
J38: Grand Total | K38: 129 | L38: 233 | P38: Grand Total | Q38: 201 | R38: 337
A45: Currently residing in which Regional Council? | B45: Southern (Karachi / Interior Sindh)
A47: Count of Name | B47: Column Labels
A48: Row Labels | B48: On Zero % | C48: <20% | D48: <30% | E48: <40% | F48: <50% | G48: <75% | H48: <85% | I48: <99% | J48: On 100% | K48: Grand Total
A49: Google Data Analytics | B49: 80 | C49: 32 | D49: 10 | E49: 12 | F49: 12 | G49: 16 | I49: 1 | J49: 15 | K49: 178
A50: Google AI Essentials | B50: 34 | C50: 11 | E50: 2 | G50: 2 | H50: 3 | J50: 86 | K50: 138
A51: Google Digital Marketing & E-commerce | B51: 60 | C51: 15 | D51: 11 | E51: 10 | F51: 9 | G51: 8 | J51: 20 | K51: 133
A52: Google Project Management | B52: 34 | C52: 13 | D52: 9 | F52: 10 | G52: 11 | H52: 1 | J52: 12 | K52: 90
A53: Google Prompting Essentials | B53: 27 | D53: 8 | F53: 5 | G53: 2 | J53: 45 | K53: 87
A54: Google Cybersecurity | B54: 27 | C54: 8 | D54: 1 | E54: 5 | F54: 3 | G54: 9 | H54: 1 | J54: 7 | K54: 61
A55: Google Advanced Data Analytics | B55: 25 | C55: 7 | D55: 4 | G55: 2 | J55: 7 | K55: 45
A56: Google IT Support | B56: 16 | C56: 8 | E56: 1 | G56: 1 | J56: 6 | K56: 32
A57: Google Business Intelligence | B57: 14 | D57: 5 | F57: 1 | J57: 5 | K57: 25
A58: Google IT Automation with Python | B58: 10 | C58: 6 | D58: 1 | F58: 1 | H58: 3 | J58: 3 | K58: 24
A59: Google UX Design | B59: 5 | C59: 8 | E59: 3 | F59: 1 | G59: 1 | J59: 5 | K59: 23
A60: Google Marketing Digital e E-Commerce | B60: 3 | K60: 3
A61: Google Data Analysis with Python | B61: 1 | K61: 1
A62: Grand Total | B62: 336 | C62: 108 | D62: 49 | E62: 33 | F62: 42 | G62: 52 | H62: 8 | I62: 1 | J62: 211 | K62: 840

Sheet Data
A1: Count for Enrollment | B1: Count for Yes | C1: One verses Program Registered | D1: Count for Candiodates started course | E1: Unique Id | F1: Serial no. | G1: Name | H1: Email | I1: External Id | J1: Specialization | K1: Specialization Slug | L1: University | M1: Enrollment Time | N1: Last Specialization Activity Time | O1: # Completed Courses | P1: # Courses in Specialization | Q1: Completed | R1: Removed From Program | S1: Program Slug | T1: Program Name | U1: Enrollment Source | V1: Specialization Completion Time | W1: Specialization Certificate URL | X1: Is Contract Active | Y1: Last Year Enrollment | Z1: Completion % | AA1: Completion Range | AB1: Your Phone Number Please enter your contact number in the following format: 0300xxxxxxx (11 digits)* | AC1: CNIC as per Master Data | AD1: Date of Birth | AE1: Currently residing in which Regional Council? | AF1: Local Council? | AG1: Jk currently attending? | AH1: Gender | AI1: Marital Status | AJ1: What is your current Profession? | AK1: Family Income Band | AL1: Future Interest regarding Placement | AM1: Age Bracket | AN1: Qualification
A2: 1 | B2: 0 | C2: 1 | D2: 1 | E2: tahirsahil807@gmail.comGoogle Project Management | F2: 1 | G2: Tahir Hussain | H2: tahirsahil807@gmail.com | I2: 7140199480925 | J2: Google Project Management | K2: google-project-management | L2: Google | M2: 2025-07-24T03:27:06.743Z | N2: 2025-07-24T04:01:20.611Z | O2: 0 | P2: 7 | Q2: No | R2: No | S2: akepb-gilgit-male-gxr0q | T2: AKEPB - Gilgit II (Male) | Y2: No | Z2: 0 | AA2: On Zero % | AB2: +923160895010 | AC2: 7140199480925 | AD2: 34982 | AE2: Gilgit | AF2: Gilgit_Gilgit Region | AG2: Noorabad jamatkhana | AH2: Male | AI2: Married | AJ2: Self Employed | AK2: 25,000 - 50,000 | AL2: Support My Family members for Upskilling | AM2: 26-35 | AN2: Masters
A3: 1 | B3: 0 | C3: 1 | D3: 1 | E3: nizarbahadur65@gmail.comGoogle Data Analytics | F3: 2 | G3: Nizar Bahadur | H3: nizarbahadur65@gmail.com | I3: 7140240244219 | J3: Google Data Analytics | K3: google-data-analytics | L3: Google | M3: 2025-08-22T07:08:44.148Z | N3: 2025-09-21T07:41:19.439Z | O3: 0 | P3: 9 | Q3: No | R3: No | S3: akepb-central-male-qoy2h | T3: AKEPB - Central (Male) | U3: Google Career Certificates Scholarship Program | Y3: No | Z3: 0 | AA3: On Zero % | AB3: +923169546084 | AC3: 7140240244219 | AD3: 38148 | AE3: Central (Rawalpindi / Lahore / Interior Punjab / Peshawar / etc) | AF3: Peshawar_Central Region | AG3: Amin colony JK | AH3: Male | AI3: Single | AJ3: Student | AK3: 80,001 - 100,000 | AL3: Advanced technical or soft skills training | AM3: 18-25 | AN3: Bachelors
A4: 1 | B4: 0 | C4: 1 | D4: 1 | E4: riazhaikal44@gmail.comGoogle Cybersecurity | F4: 3 | G4: Riazahmad | H4: riazhaikal44@gmail.com | I4: 7170203427469 | J4: Google Cybersecurity | K4: google-cybersecurity | L4: Google | M4: 2025-08-04T16:22:12.487Z | O4: 0 | P4: 9 | Q4: No | R4: No | S4: akepb-central-male-qoy2h | T4: AKEPB - Central (Male) | U4: Google Career Certificates Scholarship Program | V4: GgvHw | Y4: No | Z4: 0 | AA4: On Zero % | AB4: +923170566335 | AC4: 7170203427469 | AD4: 37398 | AE4: Central (Rawalpindi / Lahore / Interior Punjab / Peshawar / etc) | AF4: Rawalpindi_Central Region | AG4: Apara jk | AH4: Male | AI4: Single | AJ4: Student | AK4: 60,000 - 80,000 | AL4: Advanced technical or soft skills training | AM4: 18-25 | AN4: FSc
A5: 0 | B5: 1 | D5: 0 | E5: hasnain.ux@gmail.comGoogle Project Management | F5: 4 | G5: Hasnain Karim | H5: hasnain.ux@gmail.com | I5: 7170303412029 | J5: Google Project Management | K5: google-project-management | L5: Google | M5: 2025-09-03T14:30:29.941Z | N5: 2025-10-16T08:17:33.646Z | O5: 1 | P5: 7 | Q5: No | R5: No | S5: akepb-gilgit-male-gxr0q | T5: AKEPB - Gilgit II (Male) | U5: Google Career Certificates Scholarship Program | V5: xCh7v | Y5: No | Z5: 0.14285714 | AA5: <20% | AB5: +923465760321 | AC5: 7170303412029 | AD5: 37194 | AE5: Gilgit | AF5: Gilgit_Gilgit Region | AG5: Sonikot | AH5: Male | AI5: Single | AJ5: Employed | AK5: 25,000 - 50,000 | AL5: Support My Family members for Upskilling | AM5: 18-25 | AN5: FSc
A6: 1 | B6: 0 | C6: 1 | D6: 1 | E6: alirajpootuk0@gmail.comGoogle Data Analytics | F6: 5 | G6: Ali Hussnain | H6: alirajpootuk0@gmail.com | I6: 3430125604137 | J6: Google Data Analytics | K6: google-data-analytics | L6: Google | M6: 2025-07-23T19:24:26.198Z | N6: 2025-11-03T22:18:08.344Z | O6: 1 | P6: 9 | Q6: No | R6: No | S6: akepb-central-male-qoy2h | T6: AKEPB - Central (Male) | U6: Google Career Certificates Scholarship Program | Y6: No | Z6: 0.11111111 | AA6: <20% | AB6: +923472055937 | AC6: 3430125604137 | AD6: 33912 | AE6: Central (Rawalpindi / Lahore / Interior Punjab / Peshawar / etc) | AF6: Hafizabad_Central Region | AG6: Main jk | AH6: Male | AI6: Married | AJ6: Employed | AK6: 25,000 - 50,000 | AL6: Support My Family members for Upskilling | AM6: 26-35 | AN6: FSc
A7: 1 | B7: 0 | C7: 1 | D7: 1 | E7: knameera825@gmail.comGoogle Data Analytics | F7: 6 | G7: Nameera khan | H7: knameera825@gmail.com | I7: 4240159619200 | J7: Google Data Analytics | K7: google-data-analytics | L7: Google | M7: 2025-07-29T10:36:49.216Z | N7: 2025-10-31T07:45:39.624Z | O7: 5 | P7: 9 | Q7: No | R7: No | S7: akepb-gilgit-female-1kkb4 | T7: AKEPB - Gilgit II (Female) | U7: Google Career Certificates Scholarship Program | V7: xCh7v | Y7: No | Z7: 0.55555556 | AA7: <75% | AB7: +923434000818 | AC7: 4240159619200 | AD7: 36972 | AE7: Gilgit | AF7: Gilgit_Gilgit Region | AG7: jamatkhana # 03 Nomal | AH7: Female | AI7: Single | AJ7: Fresh Graduate | AK7: 60,000 - 80,000 | AL7: Advanced technical or soft skills training | AM7: 18-25 | AN7: Below Matric
A8: 0 | B8: 0 | D8: 0 | E8: siduuusidra2006@gmail.comGoogle Project Management | F8: 7 | G8: Sidar Tul Muntaha | H8: siduuusidra2006@gmail.com | I8: 7140305827396 | J8: Google Project Management | K8: google-project-management | L8: Google | M8: 2025-08-04T11:46:00.022Z | N8: 2025-08-04T12:20:40.715Z | O8: 0 | P8: 7 | Q8: No | R8: No | S8: akepb-central-female-g5ddm | T8: AKEPB - Central (Female) | V8: xCh7v | Y8: No | Z8: 0 | AA8: On Zero % | AB8: +923197829316 | AC8: 7140305827396 | AD8: 38786 | AE8: Central (Rawalpindi / Lahore / Interior Punjab / Peshawar / etc) | AF8: Rawalpindi_Central Region | AG8: Rawalpindi JK | AH8: Female | AI8: Single | AJ8: Student | AK8: 25,000 - 50,000 | AL8: Internship placements | AM8: 18-25 | AN8: FSc
A9: 1 | B9: 0 | C9: 1 | D9: 1 | E9: adilkamalkhan3@gmail.comGoogle AI Essentials | F9: 8 | G9: Aadil Kamal Khan | H9: adilkamalkhan3@gmail.com | I9: 1520261333007 | J9: Google AI Essentials | K9: ai-essentials-google | L9: Google | M9: 2025-11-01T04:30:49.475Z | N9: 2025-11-01T05:52:03.425Z | O9: 1 | P9: 5 | Q9: No | R9: No | S9: akepb-central-male-qoy2h | T9: AKEPB - Central (Male) | V9: GgvHw | Y9: No | Z9: 0.2 | AA9: <20% | AB9: Not available in Google Form Data | AC9: Not available in Google Form Data | AD9: Not available in Google Form Data | AE9: Central (Rawalpindi / Lahore / Interior Punjab / Peshawar / etc) | AF9: Not available in Google Form Data | AG9: Not available in Google Form Data | AH9: Not available in Google Form Data | AI9: Not available in Google Form Data | AJ9: Not available in Google Form Data | AK9: Not available in Google Form Data | AL9: Not available in Google Form Data | AM9: Not available in Google Form Data | AN9: Not available in Google Form Data
A10: 0 | B10: 0 | D10: 0 | E10: reenaalim4@gmail.comGoogle Business Intelligence | F10: 9 | G10: Reena | H10: reenaalim4@gmail.com | I10: 7140405807386 | J10: Google Business Intelligence | K10: google-business-intelligence | L10: Google | M10: 2025-10-09T16:51:11.541Z | N10: 2025-10-09T17:06:39.912Z | O10: 0 | P10: 3 | Q10: No | R10: No | S10: akepb-gilgit-female-1kkb4 | T10: AKEPB - Gilgit II (Female) | U10: Google Career Certificates Scholarship Program | V10: GgvHw | Y10: No | Z10: 0 | AA10: On Zero % | AB10: +923428684372 | AC10: 7140405807386 | AD10: 38717 | AE10: Gilgit | AF10: Chatoorkhand_Ishkoman & Puniyal Region | AG10: Center jamat khana Chatorkhand | AH10: Female | AI10: Single | AJ10: Student | AK10: 60,000 - 80,000 | AL10: Entrepreneurship support and mentoring | AM10: 18-25 | AN10: Bachelors
A11: 0 | B11: 0 | D11: 0 | E11: ahtishambulbul4@gmail.comGoogle Data Analytics | F11: 10 | G11: Ahtisham bulbul | H11: ahtishambulbul4@gmail.com | I11: 7140108770097 | J11: Google Data Analytics | K11: google-data-analytics | L11: Google | M11: 2025-10-16T00:41:18.854Z | O11: 0 | P11: 9 | Q11: No | R11: No | S11: akepb-central-male-qoy2h | T11: AKEPB - Central (Male) | U11: Google Career Certificates Scholarship Program | V11: xCh7v | Y11: No | Z11: 0 | AA11: On Zero % | AB11: +923488898281 | AC11: 7140108770097 | AD11: 37626 | AE11: Central (Rawalpindi / Lahore / Interior Punjab / Peshawar / etc) | AF11: Rawalpindi_Central Region | AG11: Central jamat khana rawalpindi | AH11: Male | AI11: Single | AJ11: Student | AK11: Below 25,000 | AL11: Entrepreneurship support and mentoring | AM11: 18-25 | AN11: FSc
A12: 1 | B12: 0 | C12: 1 | D12: 1 | E12: zeeshanwazir339@gmail.comGoogle Advanced Data Analytics | F12: 11 | G12: Zeeshan wazir | H12: zeeshanwazir339@gmail.com | I12: 7140303544757 | J12: Google Advanced Data Analytics | K12: google-advanced-data-analytics | L12: Google | M12: 2025-08-09T08:14:44.586Z | N12: 2025-11-02T08:21:54.307Z | O12: 5 | P12: 8 | Q12: No | R12: No | S12: akepb-gilgit-male-gxr0q | T12: AKEPB - Gilgit II (Male) | V12: xCh7v | Y12: No | Z12: 0.625 | AA12: <75% | AB12: +923555641737 | AC12: 7140303544757 | AD12: 37323 | AE12: Gilgit | AF12: Gilgit_Gilgit Region | AG12: sonikot | AH12: Male | AI12: Single | AJ12: Student | AK12: 60,000 - 80,000 | AL12: Job referrals or placement support | AM12: 18-25 | AN12: FSc
A13: 0 | B13: 0 | D13: 0 | E13: mahmud.shah@akhsp.orgGoogle IT Support | F13: 12 | G13: Mahmud Shah | H13: mahmud.shah@akhsp.org | I13: 3520217529755 | J13: Google IT Support | K13: google-it-support | L13: Google | M13: 2025-08-31T18:39:25.666Z | N13: 2025-09-28T01:59:16.808Z | O13: 0 | P13: 6 | Q13: No | R13: No | S13: akepb-central-male-qoy2h | T13: AKEPB - Central (Male) | V13: xCh7v | Y13: No | Z13: 0 | AA13: On Zero % | AB13: +923495423229 | AC13: 3520217529755 | AD13: 25569 | AE13: Central (Rawalpindi / Lahore / Interior Punjab / Peshawar / etc) | AF13: Rawalpindi_Central Region | AG13: Rawalpindi | AH13: Male | AI13: Married | AJ13: Employed | AK13: 100,001 - 120,000 | AL13: Enhance my skills in my current job | AM13: 46 and above | AN13: Masters
A14: 0 | B14: 0 | D14: 0 | E14: alisherctl.99@gmail.comGoogle Digital Marketing & E-commerce | F14: 13 | G14: Ali sher | H14: alisherctl.99@gmail.com | I14: 1520146085765 | J14: Google Digital Marketing & E-commerce | K14: google-digital-marketing-ecommerce | L14: Google | M14: 2025-10-05T18:47:12.628Z | O14: 0 | P14: 8 | Q14: No | R14: No | S14: akepb-central-male-qoy2h | T14: AKEPB - Central (Male) | U14: Google Career Certificates Scholarship Program | V14: xCh7v | Y14: No | Z14: 0 | AA14: On Zero % | AB14: +923449539220 | AC14: 1520146085765 | AD14: 37704 | AE14: Central (Rawalpindi / Lahore / Interior Punjab / Peshawar / etc) | AF14: Rawalpindi_Central Region | AG14: Golden jubilee jk rawalpindi | AH14: Male | AI14: Single | AJ14: Student | AK14: Below 25,000 | AL14: Participation in hackathons and innovation challenges | AM14: 18-25 | AN14: Bachelors
A15: 1 | B15: 0 | C15: 1 | D15: 1 | E15: inaararashmal@gmail.comGoogle Data Analytics | F15: 14 | G15: Inaara Murad | H15: inaararashmal@gmail.com | I15: 7140405746476 | J15: Google Data Analytics | K15: google-data-analytics | L15: Google | M15: 2025-07-23T12:29:27.236Z | N15: 2025-09-21T06:31:26.184Z | O15: 1 | P15: 9 | Q15: No | R15: No | S15: akepb-central-female-g5ddm | T15: AKEPB - Central (Female) | U15: Google Career Certificates Scholarship Program | Y15: No | Z15: 0.11111111 | AA15: <20% | AB15: +923554580112 | AC15: 7140405746476 | AD15: 37819 | AE15: Central (Rawalpindi / Lahore / Interior Punjab / Peshawar / etc) | AF15: Rawalpindi_Central Region | AG15: G9 karimabad jamatkhana | AH15: Female | AI15: Single | AJ15: Student | AK15: 25,000 - 50,000 | AL15: Internship placements | AM15: 18-25 | AN15: Bachelors
A16: 1 | B16: 0 | C16: 1 | D16: 1 | E16: alizubia62@gmail.comGoogle Data Analytics | F16: 15 | G16: Zubia Ali | H16: alizubia62@gmail.com | I16: 7140277375268 | J16: Google Data Analytics | K16: google-data-analytics | L16: Google | M16: 2025-08-02T22:55:03.202Z | N16: 2025-11-03T18:49:45.039Z | O16: 2 | P16: 9 | Q16: No | R16: No | S16: akepb-central-female-g5ddm | T16: AKEPB - Central (Female) | U16: Google Career Certificates Scholarship Program | Y16: No | Z16: 0.22222222 | AA16: <30% | AB16: +923169163008 | AC16: 7140277375268 | AD16: 38353 | AE16: Central (Rawalpindi / Lahore / Interior Punjab / Peshawar / etc) | AF16: Rawalpindi_Central Region | AG16: Pindi jamat khana | AH16: Female | AI16: Single | AJ16: Student | AK16: 60,000 - 80,000 | AL16: Advanced technical or soft skills training | AM16: 18-25 | AN16: Bachelors
A17: 1 | B17: 0 | C17: 1 | D17: 1 | E17: emanjehangir004@gmail.comGoogle Project Management | F17: 16 | G17: Eman Jehangir | H17: emanjehangir004@gmail.com | I17: 6110108021780 | J17: Google Project Management | K17: google-project-management | L17: Google | M17: 2025-07-26T14:17:18.803Z | O17: 0 | P17: 7 | Q17: No | R17: No | S17: akepb-central-female-g5ddm | T17: AKEPB - Central (Female) | V17: GgvHw | Y17: No | Z17: 0 | AA17: On Zero % | AB17: +923421502759 | AC17: 6110108021780 | AD17: 38230 | AE17: Central (Rawalpindi / Lahore / Interior Punjab / Peshawar / etc) | AF17: Rawalpindi_Central Region | AG17: Karimabad G-9 Jammatkhana | AH17: Female | AI17: Single | AJ17: Student | AK17: 80,001 - 100,000 | AL17: Advanced technical or soft skills training | AM17: 18-25 | AN17: FSc
A18: 0 | B18: 0 | D18: 0 | E18: nazeeraman93@gmail.comGoogle AI Essentials | F18: 17 | G18: Nazeer Aman | H18: nazeeraman93@gmail.com | I18: 7140253332139 | J18: Google AI Essentials | K18: ai-essentials-google | L18: Google | M18: 2025-07-23T10:07:01.489Z | N18: 2025-07-27T10:22:06.545Z | O18: 1 | P18: 5 | Q18: No | R18: No | S18: akepb-central-male-qoy2h | T18: AKEPB - Central (Male) | U18: Google Career Certificates Scholarship Program | V18: GgvHw | Y18: No | Z18: 0.2 | AA18: <20% | AB18: +923170580327 | AC18: 7140253332139 | AD18: 36589 | AE18: Central (Rawalpindi / Lahore / Interior Punjab / Peshawar / etc) | AF18: Rawalpindi_Central Region | AG18: Ismaili Jamatkhanaa Chandi Chowk Rawalpindi | AH18: Male | AI18: Single | AJ18: Unemployed | AK18: 25,000 - 50,000 | AL18: Advanced technical or soft skills training | AM18: 18-25 | AN18: Bachelors
A19: 0 | B19: 1 | D19: 0 | E19: hafsarehmat803@gmail.comGoogle Cybersecurity | F19: 18 | G19: Hafsa Rehmat | H19: hafsarehmat803@gmail.com | I19: 3840386030338 | J19: Google Cybersecurity | K19: google-cybersecurity | L19: Google | M19: 2025-07-23T18:44:42.350Z | N19: 2025-10-08T18:45:16.157Z | O19: 4 | P19: 9 | Q19: No | R19: No | S19: akepb-central-female-g5ddm | T19: AKEPB - Central (Female) | U19: Google Career Certificates Scholarship Program | V19: GgvHw | Y19: No | Z19: 0.44444444 | AA19: <50% | AB19: +923369416909 | AC19: 3840386030338 | AD19: 37865 | AE19: Central (Rawalpindi / Lahore / Interior Punjab / Peshawar / etc) | AF19: Rawalpindi_Central Region | AG19: Karimabad Jamat Khana Islamabad | AH19: Female | AI19: Single | AJ19: Student | AK19: 80,001 - 100,000 | AL19: Internship placements | AM19: 18-25 | AN19: FSc
A20: 0 | B20: 0 | D20: 0 | E20: alisherctl.99@gmail.comGoogle AI Essentials | F20: 19 | G20: Ali sher | H20: alisherctl.99@gmail.com | I20: 1520146085765 | J20: Google AI Essentials | K20: ai-essentials-google | L20: Google | M20: 2025-10-05T18:46:06.975Z | O20: 0 | P20: 5 | Q20: No | R20: No | S20: akepb-central-male-qoy2h | T20: AKEPB - Central (Male) | U20: Google Career Certificates Scholarship Program | V20: GgvHw | Y20: No | Z20: 0 | AA20: On Zero % | AB20: +923449539220 | AC20: 1520146085765 | AD20: 37704 | AE20: Central (Rawalpindi / Lahore / Interior Punjab / Peshawar / etc) | AF20: Rawalpindi_Central Region | AG20: Golden jubilee jk rawalpindi | AH20: Male | AI20: Single | AJ20: Student | AK20: Below 25,000 | AL20: Participation in hackathons and innovation challenges | AM20: 18-25 | AN20: Bachelors
A21: 0 | B21: 0 | D21: 0 | E21: uzmaaly0@gmail.comGoogle Data Analytics | F21: 20 | G21: Uzma paree | H21: uzmaaly0@gmail.com | I21: 7170305662552 | J21: Google Data Analytics | K21: google-data-analytics | L21: Google | M21: 2025-09-16T08:39:28.187Z | O21: 0 | P21: 9 | Q21: No | R21: No | S21: akepb-gilgit-female-1kkb4 | T21: AKEPB - Gilgit II (Female) | Y21: No | Z21: 0 | AA21: On Zero % | AB21: +923415766809 | AC21: 7170305662552 | AD21: 37244 | AE21: Gilgit | AF21: Gilgit_Gilgit Region | AG21: Zulifiqarabad jamatkhana | AH21: Female | AI21: Single | AJ21: Fresh Graduate | AK21: 60,000 - 80,000 | AL21: Support My Family members for Upskilling | AM21: 18-25 | AN21: Bachelors
A22: 1 | B22: 0 | C22: 1 | D22: 1 | E22: djhassanali986@gmail.comGoogle Data Analytics | F22: 21 | G22: Hassan ali | H22: djhassanali986@gmail.com | I22: 1520288940049 | J22: Google Data Analytics | K22: google-data-analytics | L22: Google | M22: 2025-07-24T03:12:45.799Z | N22: 2025-08-16T15:25:32.301Z | O22: 0 | P22: 9 | Q22: No | R22: No | S22: akepb-central-male-qoy2h | T22: AKEPB - Central (Male) | U22: Google Career Certificates Scholarship Program | V22: xCh7v | Y22: No | Z22: 0 | AA22: On Zero % | AB22: +923409860828 | AC22: 1520288940049 | AD22: 34390 | AE22: Central (Rawalpindi / Lahore / Interior Punjab / Peshawar / etc) | AF22: Rawalpindi_Central Region | AG22: Chandni chowk | AH22: Male | AI22: Single | AJ22: Employed | AK22: 60,000 - 80,000 | AL22: Job referrals or placement support | AM22: 26-35 | AN22: Masters
A23: 1 | B23: 0 | C23: 1 | D23: 1 | E23: shsaleemraza@gmail.comGoogle Project Management | F23: 22 | G23: Sheikh Saleem Raza | H23: shsaleemraza@gmail.com | I23: 3520227250785 | J23: Google Project Management | K23: google-project-management | L23: Google | M23: 2025-07-27T11:38:51.830Z | N23: 2025-07-27T11:47:00.632Z | O23: 0 | P23: 7 | Q23: No | R23: No | S23: akepb-central-male-qoy2h | T23: AKEPB - Central (Male) | U23: Google Career Certificates Scholarship Program | Y23: No | Z23: 0 | AA23: On Zero % | AB23: +923344010205 | AC23: 3520227250785 | AD23: 26394 | AE23: Central (Rawalpindi / Lahore / Interior Punjab / Peshawar / etc) | AF23: Lahore_Central Region | AG23: Lahore | AH23: Male | AI23: Married | AJ23: Employed | AK23: 180,000 - 200,000 | AL23: Advanced technical or soft skills training | AM23: 46 and above | AN23: Bachelors
A24: 0 | B24: 0 | D24: 0 | E24: sabiraansari54@gmail.comGoogle Data Analytics | F24: 23 | G24: Sabira Ansari | H24: sabiraansari54@gmail.com | I24: 1520290086362 | J24: Google Data Analytics | K24: google-data-analytics | L24: Google | M24: 2025-08-12T06:36:34.428Z | N24: 2025-10-29T10:18:16.496Z | O24: 6 | P24: 9 | Q24: No | R24: No | S24: akepb-central-female-g5ddm | T24: AKEPB - Central (Female) | V24: GgvHw | Y24: No | Z24: 0.66666667 | AA24: <75% | AB24: +923423325057 | AC24: 1520290086362 | AD24: 35471 | AE24: Central (Rawalpindi / Lahore / Interior Punjab / Peshawar / etc) | AF24: Rawalpindi_Central Region | AG24: Rawalpindi chandi Chowk | AH24: Female | AI24: Single | AJ24: Fresh Graduate | AK24: 60,000 - 80,000 | AL24: Entrepreneurship support and mentoring | AM24: 26-35 | AN24: Bachelors
A25: 1 | B25: 0 | C25: 1 | D25: 1 | E25: jibranali1112@gmail.comGoogle Digital Marketing & E-commerce | F25: 24 | G25: Jibran ali | H25: jibranali1112@gmail.com | I25: 7170203457325 | J25: Google Digital Marketing & E-commerce | K25: google-digital-marketing-ecommerce | L25: Google | M25: 2025-07-24T06:42:30.403Z | N25: 2025-11-02T10:27:42.294Z | O25: 2 | P25: 8 | Q25: No | R25: No | S25: akepb-gilgit-male-gxr0q | T25: AKEPB - Gilgit II (Male) | V25: xCh7v | Y25: No | Z25: 0.25 | AA25: <30% | AB25: +923144464908 | AC25: 7170203457325 | AD25: 37946 | AE25: Gilgit | AF25: Gilgit_Gilgit Region | AG25: Center jk | AH25: Male | AI25: Single | AJ25: Student | AK25: 80,001 - 100,000 | AL25: Entrepreneurship support and mentoring | AM25: 18-25 | AN25: FSc
A26: 0 | B26: 0 | D26: 0 | E26: Mubashiranwar95@gmail.comGoogle Cybersecurity | F26: 25 | G26: Mubashir Anwar | H26: Mubashiranwar95@gmail.com | I26: 1520252980589 | J26: Google Cybersecurity | K26: google-cybersecurity | L26: Google | M26: 2025-10-04T14:37:34.024Z | N26: 2025-10-04T15:17:20.808Z | O26: 0 | P26: 9 | Q26: No | R26: No | S26: akepb-central-male-qoy2h | T26: AKEPB - Central (Male) | U26: Google Career Certificates Scholarship Program | Y26: No | Z26: 0 | AA26: On Zero % | AB26: +923468069062 | AC26: 1520252980589 | AD26: 38062 | AE26: Central (Rawalpindi / Lahore / Interior Punjab / Peshawar / etc) | AF26: Peshawar_Central Region | AG26: Sikandar Town | AH26: Male | AI26: Single | AJ26: Student | AK26: 25,000 - 50,000 | AL26: Advanced technical or soft skills training | AM26: 18-25 | AN26: FSc
A27: 0 | B27: 0 | D27: 0 | E27: mashal.bsse@gmail.comGoogle IT Support | F27: 26 | G27: Mashal Ud din | H27: mashal.bsse@gmail.com | I27: 7150197972564 | J27: Google IT Support | K27: google-it-support | L27: Google | M27: 2025-07-25T06:51:36.917Z | N27: 2025-07-28T10:41:39.720Z | O27: 0 | P27: 6 | Q27: No | R27: No | S27: akepb-central-female-g5ddm | T27: AKEPB - Central (Female) | V27: GgvHw | Y27: No | Z27: 0 | AA27: On Zero % | AB27: +923466665110 | AC27: 7150197972564 | AD27: 36343 | AE27: Central (Rawalpindi / Lahore / Interior Punjab / Peshawar / etc) | AF27: Rawalpindi_Central Region | AG27: Rawalpindi JK | AH27: Female | AI27: Single | AJ27: Unemployed | AK27: 80,001 - 100,000 | AL27: Job referrals or placement support | AM27: 26-35 | AN27: Bachelors
A28: 0 | B28: 0 | D28: 0 | E28: waqas.ferwani198@gmail.comGoogle Data Analytics | F28: 27 | G28: waqas Ahmed | H28: waqas.ferwani198@gmail.com | I28: 7140261418847 | J28: Google Data Analytics | K28: google-data-analytics | L28: Google | M28: 2025-08-26T17:12:03.381Z | O28: 0 | P28: 9 | Q28: No | R28: No | S28: akepb-central-male-qoy2h | T28: AKEPB - Central (Male) | U28: Google Career Certificates Scholarship Program | V28: xCh7v | Y28: No | Z28: 0 | AA28: On Zero % | AB28: +923440562209 | AC28: 7140261418847 | AD28: 35828 | AE28: Central (Rawalpindi / Lahore / Interior Punjab / Peshawar / etc) | AF28: Rawalpindi_Central Region | AG28: Rawalpindi jk | AH28: Male | AI28: Single | AJ28: Employed | AK28: 100,001 - 120,000 | AL28: Entrepreneurship support and mentoring | AM28: 26-35 | AN28: FSc
A29: 0 | B29: 0 | D29: 0 | E29: azaamcna@gmail.comGoogle Project Management | F29: 28 | G29: Azaam | H29: azaamcna@gmail.com | I29: 1310166204003 | J29: Google Project Management | K29: google-project-management | L29: Google | M29: 2025-07-24T11:00:39.005Z | O29: 0 | P29: 6 | Q29: No | R29: No | S29: akepb-central-male-qoy2h | T29: AKEPB - Central (Male) | V29: xCh7v | Y29: No | Z29: 0 | AA29: On Zero % | AB29: +923279172151 | AC29: 1310166204003 | AD29: 37830 | AE29: Central (Rawalpindi / Lahore / Interior Punjab / Peshawar / etc) | AF29: Peshawar_Central Region | AG29: Abbottabad | AH29: Male | AI29: Single | AJ29: Student | AK29: 25,000 - 50,000 | AL29: Entrepreneurship support and mentoring | AM29: 18-25 | AN29: FSc
A30: 1 | B30: 0 | C30: 1 | D30: 1 | E30: inbox.sideeq@gmail.comGoogle Digital Marketing & E-commerce | F30: 29 | G30: Sideeq Akbar | H30: inbox.sideeq@gmail.com | I30: 1520257488921 | J30: Google Digital Marketing & E-commerce | K30: google-digital-marketing-ecommerce | L30: Google | M30: 2025-07-30T18:47:01.829Z | N30: 2025-07-30T19:31:38.124Z | O30: 0 | P30: 8 | Q30: No | R30: No | S30: akepb-central-male-qoy2h | T30: AKEPB - Central (Male) | U30: Google Career Certificates Scholarship Program | V30: xCh7v | Y30: No | Z30: 0 | AA30: On Zero % | AB30: +923409860749 | AC30: 1520257488921 | AD30: 35462 | AE30: Central (Rawalpindi / Lahore / Interior Punjab / Peshawar / etc) | AF30: Rawalpindi_Central Region | AG30: Rwp | AH30: Male | AI30: Single | AJ30: Employed | AK30: 60,000 - 80,000 | AL30: Entrepreneurship support and mentoring | AM30: 26-35 | AN30: Bachelors
A31: 0 | B31: 0 | D31: 0 | E31: zk311984@gmail.comGoogle Data Analytics | F31: 30 | G31: zahra khan | H31: zk311984@gmail.com | I31: 7170205711780 | J31: Google Data Analytics | K31: google-data-analytics | L31: Google | M31: 2025-07-26T04:20:55.932Z | N31: 2025-10-05T18:23:29.020Z | O31: 8 | P31: 9 | Q31: No | R31: No | S31: akepb-central-female-g5ddm | T31: AKEPB - Central (Female) | U31: Google Career Certificates Scholarship Program | Y31: No | Z31: 0.88888889 | AA31: <99% | AB31: +923181590695 | AC31: 7170205711780 | AD31: 37875 | AE31: Central (Rawalpindi / Lahore / Interior Punjab / Peshawar / etc) | AF31: Rawalpindi_Central Region | AG31: rawalpindi | AH31: Female | AI31: Single | AJ31: Unemployed | AK31: 80,001 - 100,000 | AL31: Job referrals or placement support | AM31: 18-25 | AN31: Bachelors
A32: 0 | B32: 0 | D32: 0 | E32: shahnazaliciqam@gmail.comGoogle Project Management | F32: 31 | G32: shehnaz | H32: shahnazaliciqam@gmail.com | I32: 7150264081608 | J32: Google Project Management | K32: google-project-management | L32: Google | M32: 2025-09-26T09:29:34.243Z | N32: 2025-09-27T12:22:05.182Z | O32: 1 | P32: 7 | Q32: No | R32: No | S32: akepb-central-female-g5ddm | T32: AKEPB - Central (Female) | U32: Google Career Certificates Scholarship Program | V32: GgvHw | Y32: No | Z32: 0.14285714 | AA32: <20% | AB32: +923180055149 | AC32: 7150264081608 | AD32: 35888 | AE32: Central (Rawalpindi / Lahore / Interior Punjab / Peshawar / etc) | AF32: Rawalpindi_Central Region | AG32: G9 | AH32: Female | AI32: Single | AJ32: Employed | AK32: 25,000 - 50,000 | AL32: Advanced technical or soft skills training | AM32: 26-35 | AN32: Bachelors
A33: 0 | B33: 0 | D33: 0 | E33: healthbytes024@gmail.comGoogle AI Essentials | F33: 32 | G33: Piyar Ali | H33: healthbytes024@gmail.com | I33: 7140303507631 | J33: Google AI Essentials | K33: ai-essentials-google | L33: Google | M33: 2025-10-27T17:42:42.273Z | N33: 2025-10-27T18:46:38.369Z | O33: 1 | P33: 5 | Q33: No | R33: No | S33: akepb-central-male-qoy2h | T33: AKEPB - Central (Male) | U33: Google Career Certificates Scholarship Program | V33: xCh7v | Y33: No | Z33: 0.2 | AA33: <20% | AB33: +923414136972 | AC33: 7140303507631 | AD33: 36753 | AE33: Central (Rawalpindi / Lahore / Interior Punjab / Peshawar / etc) | AF33: Lahore_Central Region | AG33: Lahore Davis Road | AH33: Male | AI33: Single | AJ33: Self Employed | AK33: 80,001 - 100,000 | AL33: Internship placements | AM33: 26-35 | AN33: FSc
A34: 0 | B34: 2 | D34: 0 | E34: girmmeen@gmail.comGoogle Data Analytics | F34: 33 | G34: Wajahat Sultan | H34: girmmeen@gmail.com | I34: 7140195844331 | J34: Google Data Analytics | K34: google-data-analytics | L34: Google | M34: 2025-10-24T11:58:55.453Z | N34: 2025-10-25T11:41:02.297Z | O34: 1 | P34: 9 | Q34: No | R34: No | S34: akepb-central-male-qoy2h | T34: AKEPB - Central (Male) | U34: Google Career Certificates Scholarship Program | V34: xCh7v | Y34: No | Z34: 0.11111111 | AA34: <20% | AB34: +923488146815 | AC34: 7140195844331 | AD34: 34069 | AE34: Central (Rawalpindi / Lahore / Interior Punjab / Peshawar / etc) | AF34: Rawalpindi_Central Region | AG34: Chandni Chowk Rwp | AH34: Male | AI34: Married | AJ34: Employed | AK34: 80,001 - 100,000 | AL34: Advanced technical or soft skills training | AM34: 26-35 | AN34: Masters
A35: 1 | B35: 0 | C35: 1 | D35: 1 | E35: alihmzazia@gmail.comGoogle Data Analytics | F35: 34 | G35: Ali Hamza Zia | H35: alihmzazia@gmail.com | I35: 3430186976493 | J35: Google Data Analytics | K35: google-data-analytics | L35: Google | M35: 2025-07-23T12:39:10.010Z | N35: 2025-08-16T03:13:39.378Z | O35: 0 | P35: 9 | Q35: No | R35: No | S35: akepb-central-male-qoy2h | T35: AKEPB - Central (Male) | U35: Google Career Certificates Scholarship Program | V35: xCh7v | Y35: No | Z35: 0 | AA35: On Zero % | AB35: +923217973696 | AC35: 3430186976493 | AD35: 35206 | AE35: Central (Rawalpindi / Lahore / Interior Punjab / Peshawar / etc) | AF35: Lahore_Central Region | AG35: Faisalabad | AH35: Male | AI35: Married | AJ35: Self Employed | AK35: 60,000 - 80,000 | AL35: Support My Family members for Upskilling | AM35: 26-35 | AN35: Bachelors
A36: 0 | B36: 1 | D36: 0 | E36: sammuhammad289@gmail.comGoogle Data Analytics | F36: 35 | G36: Muhammad Sami | H36: sammuhammad289@gmail.com | I36: 7150257656119 | J36: Google Data Analytics | K36: google-data-analytics | L36: Google | M36: 2025-08-21T06:33:48.117Z | N36: 2025-09-24T16:37:07.853Z | O36: 0 | P36: 9 | Q36: No | R36: No | S36: akepb-central-male-qoy2h | T36: AKEPB - Central (Male) | U36: Google Career Certificates Scholarship Program | Y36: No | Z36: 0 | AA36: On Zero % | AB36: +923411840755 | AC36: 7150257656119 | AD36: 38136 | AE36: Central (Rawalpindi / Lahore / Interior Punjab / Peshawar / etc) | AF36: Rawalpindi_Central Region | AG36: Ismaili Jamatkhanaa Chandi Chowk Rawalpindi | AH36: Male | AI36: Single | AJ36: Student | AK36: 80,001 - 100,000 | AL36: Advanced technical or soft skills training | AM36: 18-25 | AN36: FSc
A37: 0 | B37: 0 | D37: 0 | E37: sa2476professional@gmail.comGoogle Data Analytics | F37: 36 | G37: Shayan Ali | H37: sa2476professional@gmail.com | I37: 6110129910499 | J37: Google Data Analytics | K37: google-data-analytics | L37: Google | M37: 2025-08-05T14:13:48.629Z | N37: 2025-10-30T13:01:35.481Z | O37: 1 | P37: 9 | Q37: No | R37: No | S37: akepb-central-male-qoy2h | T37: AKEPB - Central (Male) | V37: xCh7v | Y37: No | Z37: 0.11111111 | AA37: <20% | AB37: +923093526530 | AC37: 6110129910499 | AD37: 37631 | AE37: Central (Rawalpindi / Lahore / Interior Punjab / Peshawar / etc) | AF37: Sargodha_Central Region | AG37: Main Sargodha JK | AH37: Male | AI37: Single | AJ37: Student | AK37: 25,000 - 50,000 | AL37: Advanced technical or soft skills training | AM37: 18-25 | AN37: FSc
A38: 1 | B38: 0 | C38: 1 | D38: 1 | E38: salmanullah.baig@gmail.comGoogle IT Automation with Python | F38: 37 | G38: salman ullah baig | H38: salmanullah.baig@gmail.com | I38: 7140253806125 | J38: Google IT Automation with Python | K38: google-it-automation | L38: Google | M38: 2025-07-27T08:24:20.510Z | N38: 2025-08-25T13:50:40.306Z | O38: 0 | P38: 7 | Q38: No | R38: No | S38: akepb-central-male-qoy2h | T38: AKEPB - Central (Male) | U38: Google Career Certificates Scholarship Program | Y38: No | Z38: 0 | AA38: On Zero % | AB38: +923155597447 | AC38: 7140253806125 | AD38: 35248 | AE38: Central (Rawalpindi / Lahore / Interior Punjab / Peshawar / etc) | AF38: Rawalpindi_Central Region | AG38: G9/1 JK | AH38: Male | AI38: Single | AJ38: Self Employed | AK38: 180,000 - 200,000 | AL38: Advanced technical or soft skills training | AM38: 26-35 | AN38: Bachelors
A39: 0 | B39: 0 | D39: 0 | E39: healthbytes024@gmail.comGoogle Digital Marketing & E-commerce | F39: 38 | G39: Piyar Ali | H39: healthbytes024@gmail.com | I39: 7140303507631 | J39: Google Digital Marketing & E-commerce | K39: google-digital-marketing-ecommerce | L39: Google | M39: 2025-07-23T10:21:03.504Z | N39: 2025-09-02T19:27:40.760Z | O39: 1 | P39: 8 | Q39: No | R39: No | S39: akepb-central-male-qoy2h | T39: AKEPB - Central (Male) | U39: Google Career Certificates Scholarship Program | Y39: No | Z39: 0.125 | AA39: <20% | AB39: +923414136972 | AC39: 7140303507631 | AD39: 36753 | AE39: Central (Rawalpindi / Lahore / Interior Punjab / Peshawar / etc) | AF39: Lahore_Central Region | AG39: Lahore Davis Road | AH39: Male | AI39: Single | AJ39: Self Employed | AK39: 80,001 - 100,000 | AL39: Internship placements | AM39: 26-35 | AN39: FSc
A40: 1 | B40: 0 | C40: 1 | D40: 1 | E40: waqaralam654@gmail.comGoogle Project Management | F40: 39 | G40: Waqar Alam | H40: waqaralam654@gmail.com | I40: 7150171735503 | J40: Google Project Management | K40: google-project-management | L40: Google | M40: 2025-08-13T18:50:26.142Z | N40: 2025-08-13T20:37:57.450Z | O40: 0 | P40: 7 | Q40: No | R40: No | S40: akepb-central-male-qoy2h | T40: AKEPB - Central (Male) | U40: Google Career Certificates Scholarship Program | Y40: No | Z40: 0 | AA40: On Zero % | AB40: +923459032564 | AC40: 7150171735503 | AD40: 35961 | AE40: Central (Rawalpindi / Lahore / Interior Punjab / Peshawar / etc) | AF40: Rawalpindi_Central Region | AG40: Karimabad | AH40: Male | AI40: Single | AJ40: Student | AK40: 80,001 - 100,000 | AL40: Entrepreneurship support and mentoring | AM40: 26-35 | AN40: Masters
A41: 0 | B41: 0 | D41: 0 | E41: hamza2021karim@gmail.comGoogle Digital Marketing & E-commerce | F41: 40 | G41: Hamza Karim | H41: hamza2021karim@gmail.com | I41: 3430230923569 | J41: Google Digital Marketing & E-commerce | K41: google-digital-marketing-ecommerce | L41: Google | M41: 2023-06-17T08:14:40.235Z | N41: 2025-11-04T08:36:04.408Z | O41: 1 | P41: 8 | Q41: No | R41: No | S41: akepb-central-male-qoy2h | T41: AKEPB - Central (Male) | V41: xCh7v | Y41: No | Z41: 0.125 | AA41: <20% | AB41: +923007528942 | AC41: 3430230923569 | AD41: 37091 | AE41: Central (Rawalpindi / Lahore / Interior Punjab / Peshawar / etc) | AF41: Lahore_Central Region | AG41: Lahore | AH41: Male | AI41: Married | AJ41: Self Employed | AK41: 60,000 - 80,000 | AL41: Support My Family members for Upskilling | AM41: 18-25 | AN41: Bachelors
A42: 1 | B42: 0 | C42: 1 | D42: 1 | E42: alimadad24@gmail.comGoogle Project Management | F42: 41 | G42: ALI MADAD SHAH | H42: alimadad24@gmail.com | I42: 1520252126901 | J42: Google Project Management | K42: google-project-management | L42: Google | M42: 2025-10-28T09:17:38.986Z | N42: 2025-11-04T04:21:41.637Z | O42: 1 | P42: 7 | Q42: No | R42: No | S42: akepb-central-male-qoy2h | T42: AKEPB - Central (Male) | V42: xCh7v | Y42: No | Z42: 0.14285714 | AA42: <20% | AB42: +923338558566 | AC42: 1520252126901 | AD42: 32176 | AE42: Central (Rawalpindi / Lahore / Interior Punjab / Peshawar / etc) | AF42: Peshawar_Central Region | AG42: Skandar town | AH42: Male | AI42: Married | AJ42: Employed | AK42: 25,000 - 50,000 | AL42: Support My Family members for Upskilling | AM42: 36-45 | AN42: Bachelors
A43: 0 | B43: 0 | D43: 0 | E43: shahrules1257@gmail.comGoogle Advanced Data Analytics | F43: 42 | G43: Salman dinar | H43: shahrules1257@gmail.com | I43: 7140181125423 | J43: Google Advanced Data Analytics | K43: google-advanced-data-analytics | L43: Google | M43: 2025-07-23T14:23:40.604Z | N43: 2025-11-01T12:26:34.193Z | O43: 4 | P43: 7 | Q43: No | R43: No | S43: akepb-gilgit-male-gxr0q | T43: AKEPB - Gilgit II (Male) | U43: Google Career Certificates Scholarship Program | V43: xCh7v | Y43: No | Z43: 0.57142857 | AA43: <75% | AB43: +923165208307 | AC43: 7140181125423 | AD43: 36942 | AE43: Gilgit | AF43: Gilgit_Gilgit Region | AG43: Baladul Karim jamatkhana | AH43: Male | AI43: Single | AJ43: Fresh Graduate | AK43: 60,000 - 80,000 | AL43: Internship placements | AM43: 18-25 | AN43: Bachelors
A44: 1 | B44: 0 | C44: 1 | D44: 1 | E44: khayamdanishi@gmail.comGoogle Business Intelligence | F44: 43 | G44: KHAYAM DANISH | H44: khayamdanishi@gmail.com | I44: 7150403970093 | J44: Google Business Intelligence | K44: google-business-intelligence | L44: Google | M44: 2025-07-29T08:18:05.885Z | O44: 0 | P44: 4 | Q44: No | R44: No | S44: akepb-central-male-qoy2h | T44: AKEPB - Central (Male) | U44: Google Career Certificates Scholarship Program | Y44: No | Z44: 0 | AA44: On Zero % | AB44: +923425249896 | AC44: 7150403970093 | AD44: 34985 | AE44: Central (Rawalpindi / Lahore / Interior Punjab / Peshawar / etc) | AF44: Lahore_Central Region | AG44: Lahore | AH44: Male | AI44: Single | AJ44: Student | AK44: 80,001 - 100,000 | AL44: Advanced technical or soft skills training | AM44: 26-35 | AN44: Bachelors
A45: 0 | B45: 0 | D45: 0 | E45: ajazalishahabii@gmail.comGoogle Advanced Data Analytics | F45: 44 | G45: Ajaz Ali | H45: ajazalishahabii@gmail.com | I45: 7140135039707 | J45: Google Advanced Data Analytics | K45: google-advanced-data-analytics | L45: Google | M45: 2025-10-10T17:34:47.391Z | N45: 2025-10-11T08:26:50.282Z | O45: 0 | P45: 7 | Q45: No | R45: No | S45: akepb-gilgit-female-1kkb4 | T45: AKEPB - Gilgit II (Female) | Y45: No | Z45: 0 | AA45: On Zero % | AB45: Not available in Google Form Data | AC45: Not available in Google Form Data | AD45: Not available in Google Form Data | AE45: Gilgit | AF45: Not available in Google Form Data | AG45: Not available in Google Form Data | AH45: Not available in Google Form Data | AI45: Not available in Google Form Data | AJ45: Not available in Google Form Data | AK45: Not available in Google Form Data | AL45: Not available in Google Form Data | AM45: Not available in Google Form Data | AN45: Not available in Google Form Data
A46: 1 | B46: 0 | C46: 1 | D46: 1 | E46: faisaliqbal119@gmail.comGoogle Data Analytics | F46: 45 | G46: Faisal Iqbal | H46: faisaliqbal119@gmail.com | I46: 3660606085309 | J46: Google Data Analytics | K46: google-data-analytics | L46: Google | M46: 2025-07-28T10:57:02.588Z | N46: 2025-10-06T16:48:40.888Z | O46: 0 | P46: 8 | Q46: No | R46: No | S46: akepb-central-male-qoy2h | T46: AKEPB - Central (Male) | V46: xCh7v | Y46: No | Z46: 0 | AA46: On Zero % | AB46: +923083771744 | AC46: 3660606085309 | AD46: 34675 | AE46: Central (Rawalpindi / Lahore / Interior Punjab / Peshawar / etc) | AF46: Lahore_Central Region | AG46: Lahore | AH46: Male | AI46: Single | AJ46: Unemployed | AK46: 80,001 - 100,000 | AL46: Advanced technical or soft skills training | AM46: 26-35 | AN46: Bachelors
A47: 0 | B47: 0 | D47: 0 | E47: shahnazaliciqam@gmail.comGoogle UX Design | F47: 46 | G47: shehnaz | H47: shahnazaliciqam@gmail.com | I47: 7150264081608 | J47: Google UX Design | K47: google-ux-design | L47: Google | M47: 2025-10-08T22:39:41.752Z | O47: 0 | P47: 8 | Q47: No | R47: No | S47: akepb-central-female-g5ddm | T47: AKEPB - Central (Female) | Y47: No | Z47: 0 | AA47: On Zero % | AB47: +923180055149 | AC47: 7150264081608 | AD47: 35888 | AE47: Central (Rawalpindi / Lahore / Interior Punjab / Peshawar / etc) | AF47: Rawalpindi_Central Region | AG47: G9 | AH47: Female | AI47: Single | AJ47: Employed | AK47: 25,000 - 50,000 | AL47: Advanced technical or soft skills training | AM47: 26-35 | AN47: Bachelors
A48: 0 | B48: 0 | D48: 0 | E48: ruedad.mdk@gmail.comGoogle Data Analytics | F48: 47 | G48: Ruedad Haider | H48: ruedad.mdk@gmail.com | I48: 1520196136097 | J48: Google Data Analytics | K48: google-data-analytics | L48: Google | M48: 2025-07-27T04:45:32.020Z | N48: 2025-08-27T05:51:13.020Z | O48: 0 | P48: 9 | Q48: No | R48: No | S48: akepb-central-male-qoy2h | T48: AKEPB - Central (Male) | U48: Google Career Certificates Scholarship Program | V48: xCh7v | Y48: No | Z48: 0 | AA48: On Zero % | AB48: +923483012310 | AC48: 1520196136097 | AD48: 36457 | AE48: Central (Rawalpindi / Lahore / Interior Punjab / Peshawar / etc) | AF48: Rawalpindi_Central Region | AG48: G9, Chandni Chowk | AH48: Male | AI48: Single | AJ48: Unemployed | AK48: 140,000 - 160,000 | AL48: Advanced technical or soft skills training | AM48: 26-35 | AN48: Bachelors
A49: 1 | B49: 0 | C49: 1 | D49: 1 | E49: syedmansooralishah6552@gmail.comGoogle AI Essentials | F49: 48 | G49: SYED MANSOOR ALI SHAH | H49: syedmansooralishah6552@gmail.com | I49: 1520281384567 | J49: Google AI Essentials | K49: ai-essentials-google | L49: Google | M49: 2025-08-16T04:38:53.064Z | N49: 2025-09-13T05:11:25.601Z | O49: 1 | P49: 5 | Q49: No | R49: No | S49: akepb-central-male-qoy2h | T49: AKEPB - Central (Male) | U49: Google Career Certificates Scholarship Program | V49: xCh7v | Y49: No | Z49: 0.2 | AA49: <20% | AB49: +923431191238 | AC49: 1520281384567 | AD49: 1/10/1198 | AE49: Central (Rawalpindi / Lahore / Interior Punjab / Peshawar / etc) | AF49: Rawalpindi_Central Region | AG49: Rawalpindi | AH49: Male | AI49: Single | AJ49: Unemployed | AK49: 60,000 - 80,000 | AL49: Advanced technical or soft skills training | AM49: 26-35 | AN49: Masters
A50: 1 | B50: 0 | C50: 1 | D50: 1 | E50: shafqatullahkhangamil@gmail.comGoogle Data Analytics | F50: 49 | G50: Shafqat Ullah | H50: shafqatullahkhangamil@gmail.com | I50: 1520291687027 | J50: Google Data Analytics | K50: google-data-analytics | L50: Google | M50: 2025-09-21T07:29:24.613Z | N50: 2025-10-08T20:29:31.115Z | O50: 0 | P50: 9 | Q50: No | R50: No | S50: akepb-central-male-qoy2h | T50: AKEPB - Central (Male) | U50: Google Career Certificates Scholarship Program | Y50: No | Z50: 0 | AA50: On Zero % | AB50: +923460669427 | AC50: 1520291687027 | AD50: 38450 | AE50: Central (Rawalpindi / Lahore / Interior Punjab / Peshawar / etc) | AF50: Peshawar_Central Region | AG50: . | AH50: Male | AI50: Single | AJ50: Student | AK50: 25,000 - 50,000 | AL50: Support My Family members for Upskilling | AM50: 18-25 | AN50: FSc
A51: 0 | B51: 0 | D51: 0 | E51: israhhareem@gmail.comGoogle UX Design | F51: 50 | G51: Israh Hareem | H51: israhhareem@gmail.com | I51: 7150177202922 | J51: Google UX Design | K51: google-ux-design | L51: Google | M51: 2025-07-23T15:54:48.672Z | N51: 2025-08-13T13:37:24.527Z | O51: 1 | P51: 8 | Q51: No | R51: No | S51: akepb-gilgit-female-1kkb4 | T51: AKEPB - Gilgit II (Female) | U51: Google Career Certificates Scholarship Program | Y51: No | Z51: 0.125 | AA51: <20% | AB51: +923129935904 | AC51: 7150177202922 | AD51: 37348 | AE51: Gilgit | AF51: Gilgit_Gilgit Region | AG51: Sonikote | AH51: Female | AI51: Single | AJ51: Fresh Graduate | AK51: 60,000 - 80,000 | AL51: Job referrals or placement support | AM51: 18-25 | AN51: Bachelors
A52: 1 | B52: 0 | C52: 1 | D52: 1 | E52: aliinsha3215@gmail.comGoogle Data Analytics | F52: 51 | G52: Ali Insha | H52: aliinsha3215@gmail.com | I52: 3120159322523 | J52: Google Data Analytics | K52: google-data-analytics | L52: Google | M52: 2025-07-24T08:05:03.255Z | N52: 2025-09-15T12:08:06.260Z | O52: 0 | P52: 9 | Q52: No | R52: No | S52: akepb-central-male-qoy2h | T52: AKEPB - Central (Male) | V52: xCh7v | Y52: No | Z52: 0 | AA52: On Zero % | AB52: +923097599965 | AC52: 3120159322523 | AD52: 37842 | AE52: Central (Rawalpindi / Lahore / Interior Punjab / Peshawar / etc) | AF52: Multan & Bahawalpur_Central Region | AG52: Uch Sharif | AH52: Male | AI52: Single | AJ52: Student | AK52: 60,000 - 80,000 | AL52: in my career, helps boost my CV for article-ship. | AM52: 18-25 | AN52: FSc
A53: 0 | B53: 0 | D53: 0 | E53: sidcreative321@gmail.comGoogle IT Automation with Python | F53: 52 | G53: Sidra Amin | H53: sidcreative321@gmail.com | I53: 7150143271982 | J53: Google IT Automation with Python | K53: google-it-automation | L53: Google | M53: 2025-07-23T14:32:26.111Z | N53: 2025-09-11T10:28:05.071Z | O53: 0 | P53: 7 | Q53: No | R53: No | S53: akepb-central-female-g5ddm | T53: AKEPB - Central (Female) | U53: Google Career Certificates Scholarship Program | V53: xCh7v | Y53: No | Z53: 0 | AA53: On Zero % | AB53: +923408471422 | AC53: 7150143271982 | AD53: 37004 | AE53: Central (Rawalpindi / Lahore / Interior Punjab / Peshawar / etc) | AF53: Rawalpindi_Central Region | AG53: Rawalpindi | AH53: Female | AI53: Single | AJ53: Unemployed | AK53: 25,000 - 50,000 | AL53: Support My Family members for Upskilling | AM53: 18-25 | AN53: Bachelors
A54: 1 | B54: 0 | C54: 1 | D54: 1 | E54: aximahimmat@gmail.comGoogle Digital Marketing & E-commerce | F54: 53 | G54: Azima himat | H54: aximahimmat@gmail.com | I54: 7140164172834 | J54: Google Digital Marketing & E-commerce | K54: google-digital-marketing-ecommerce | L54: Google | M54: 2025-10-29T15:35:51.180Z | N54: 2025-10-30T19:32:27.544Z | O54: 0 | P54: 8 | Q54: No | R54: No | S54: akepb-central-female-g5ddm | T54: AKEPB - Central (Female) | V54: GgvHw | Y54: No | Z54: 0 | AA54: On Zero % | AB54: +923171981510 | AC54: 7140164172834 | AD54: 37705 | AE54: Central (Rawalpindi / Lahore / Interior Punjab / Peshawar / etc) | AF54: Rawalpindi_Central Region | AG54: G9 Jamat khana | AH54: Female | AI54: Single | AJ54: Student | AK54: 60,000 - 80,000 | AL54: Entrepreneurship support and mentoring | AM54: 18-25 | AN54: FSc
A55: 1 | B55: 0 | C55: 1 | D55: 1 | E55: shahsaleem632@gmail.comGoogle Cybersecurity | F55: 54 | G55: Shah Saleem | H55: shahsaleem632@gmail.com | I55: 7150403973405 | J55: Google Cybersecurity | K55: google-cybersecurity | L55: Google | M55: 2025-08-18T12:00:18.394Z | N55: 2025-09-20T02:24:50.660Z | O55: 0 | P55: 9 | Q55: No | R55: No | S55: akepb-central-male-qoy2h | T55: AKEPB - Central (Male) | U55: Google Career Certificates Scholarship Program | V55: xCh7v | Y55: No | Z55: 0 | AA55: On Zero % | AB55: +923437393497 | AC55: 7150403973405 | AD55: 36927 | AE55: Central (Rawalpindi / Lahore / Interior Punjab / Peshawar / etc) | AF55: Rawalpindi_Central Region | AG55: Rawalpindi JK | AH55: Male | AI55: Single | AJ55: Student | AK55: 60,000 - 80,000 | AL55: Internship placements | AM55: 18-25 | AN55: Bachelors
A56: 1 | B56: 0 | C56: 1 | D56: 1 | E56: qaboolhussain80@gmail.comGoogle Data Analytics | F56: 55 | G56: Qabool Hussain | H56: qaboolhussain80@gmail.com | I56: 7140303576735 | J56: Google Data Analytics | K56: google-data-analytics | L56: Google | M56: 2025-07-27T15:57:30.739Z | N56: 2025-10-30T22:15:24.779Z | O56: 3 | P56: 9 | Q56: No | R56: No | S56: akepb-central-male-qoy2h | T56: AKEPB - Central (Male) | U56: Google Career Certificates Scholarship Program | V56: GgvHw | Y56: No | Z56: 0.33333333 | AA56: <40% | AB56: +923181516449 | AC56: 7140303576735 | AD56: 36819 | AE56: Central (Rawalpindi / Lahore / Interior Punjab / Peshawar / etc) | AF56: Rawalpindi_Central Region | AG56: Rawalpindi | AH56: Male | AI56: Single | AJ56: Unemployed | AK56: 25,000 - 50,000 | AL56: Advanced technical or soft skills training | AM56: 18-25 | AN56: Bachelors
A57: 1 | B57: 0 | C57: 1 | D57: 1 | E57: miladkali05@gmail.comGoogle Project Management | F57: 56 | G57: Milad Kali | H57: miladkali05@gmail.com | I57: 7140405735098 | J57: Google Project Management | K57: google-project-management | L57: Google | M57: 2025-08-08T05:47:12.226Z | N57: 2025-08-08T12:36:34.836Z | O57: 0 | P57: 7 | Q57: No | R57: No | S57: akepb-gilgit-female-1kkb4 | T57: AKEPB - Gilgit II (Female) | V57: xCh7v | Y57: No | Z57: 0 | AA57: On Zero % | AB57: +923554192958 | AC57: 7140405735098 | AD57: 37035 | AE57: Gilgit | AF57: Gilgit_Gilgit Region | AG57: Yaseen colony | AH57: Female | AI57: Single | AJ57: Fresh Graduate | AK57: 25,000 - 50,000 | AL57: Job referrals or placement support | AM57: 18-25 | AN57: Masters
A58: 1 | B58: 0 | C58: 1 | D58: 1 | E58: arjumandnaz4238@gmail.comGoogle IT Support | F58: 57 | G58: Arjumand naz | H58: arjumandnaz4238@gmail.com | I58: 1520291158770 | J58: Google IT Support | K58: google-it-support | L58: Google | M58: 2025-07-25T06:01:14.076Z | N58: 2025-08-19T08:06:37.086Z | O58: 1 | P58: 6 | Q58: No | R58: No | S58: akepb-central-female-g5ddm | T58: AKEPB - Central (Female) | V58: xCh7v | Y58: No | Z58: 0.16666667 | AA58: <20% | AB58: +923423766906 | AC58: 1520291158770 | AD58: 37750 | AE58: Central (Rawalpindi / Lahore / Interior Punjab / Peshawar / etc) | AF58: Rawalpindi_Central Region | AG58: Apara G-6 Islamabad | AH58: Female | AI58: Single | AJ58: Student | AK58: 25,000 - 50,000 | AL58: Support My Family members for Upskilling | AM58: 18-25 | AN58: Bachelors
A59: 1 | B59: 0 | C59: 1 | D59: 1 | E59: miftahayub99@gmail.comGoogle Business Intelligence | F59: 58 | G59: miftah ayub | H59: miftahayub99@gmail.com | I59: 7150125180622 | J59: Google Business Intelligence | K59: google-business-intelligence | L59: Google | M59: 2025-07-31T12:48:02.248Z | N59: 2025-10-24T10:35:14.835Z | O59: 1 | P59: 4 | Q59: No | R59: No | S59: akepb-central-female-g5ddm | T59: AKEPB - Central (Female) | U59: Google Career Certificates Scholarship Program | V59: xCh7v | Y59: No | Z59: 0.25 | AA59: <30% | AB59: +923300606933 | AC59: 7150125180622 | AD59: 36156 | AE59: Central (Rawalpindi / Lahore / Interior Punjab / Peshawar / etc) | AF59: Rawalpindi_Central Region | AG59: G9 JK ISLAMABAD | AH59: Female | AI59: Single | AJ59: Employed | AK59: 180,000 - 200,000 | AL59: Entrepreneurship support and mentoring | AM59: 26-35 | AN59: Bachelors
A60: 0 | B60: 0 | D60: 0 | E60: shahrules1257@gmail.comGoogle AI Essentials | F60: 59 | G60: Salman dinar | H60: shahrules1257@gmail.com | I60: 7140181125423 | J60: Google AI Essentials | K60: ai-essentials-google | L60: Google | M60: 2025-08-24T14:32:29.485Z | O60: 0 | P60: 5 | Q60: No | R60: No | S60: akepb-gilgit-male-gxr0q | T60: AKEPB - Gilgit II (Male) | Y60: No | Z60: 0 | AA60: On Zero % | AB60: +923165208307 | AC60: 7140181125423 | AD60: 36942 | AE60: Gilgit | AF60: Gilgit_Gilgit Region | AG60: Baladul Karim jamatkhana | AH60: Male | AI60: Single | AJ60: Fresh Graduate | AK60: 60,000 - 80,000 | AL60: Internship placements | AM60: 18-25 | AN60: Bachelors
A61: 0 | B61: 0 | D61: 0 | E61: nazeeraman93@gmail.comGoogle Digital Marketing & E-commerce | F61: 60 | G61: Nazeer Aman | H61: nazeeraman93@gmail.com | I61: 7140253332139 | J61: Google Digital Marketing & E-commerce | K61: google-digital-marketing-ecommerce | L61: Google | M61: 2025-07-23T10:04:04.354Z | N61: 2025-08-06T22:00:29.752Z | O61: 0 | P61: 8 | Q61: No | R61: No | S61: akepb-central-male-qoy2h | T61: AKEPB - Central (Male) | U61: Google Career Certificates Scholarship Program | V61: GgvHw | Y61: No | Z61: 0 | AA61: On Zero % | AB61: +923170580327 | AC61: 7140253332139 | AD61: 36589 | AE61: Central (Rawalpindi / Lahore / Interior Punjab / Peshawar / etc) | AF61: Rawalpindi_Central Region | AG61: Ismaili Jamatkhanaa Chandi Chowk Rawalpindi | AH61: Male | AI61: Single | AJ61: Unemployed | AK61: 25,000 - 50,000 | AL61: Advanced technical or soft skills training | AM61: 18-25 | AN61: Bachelors
A62: 1 | B62: 0 | C62: 1 | D62: 1 | E62: akushoono514@gmail.comGoogle Digital Marketing & E-commerce | F62: 61 | G62: ABID KARIM | H62: akushoono514@gmail.com | I62: 7140268602293 | J62: Google Digital Marketing & E-commerce | K62: google-digital-marketing-ecommerce | L62: Google | M62: 2025-08-21T23:04:57.399Z | N62: 2025-08-21T23:47:09.447Z | O62: 0 | P62: 8 | Q62: No | R62: No | S62: akepb-central-male-qoy2h | T62: AKEPB - Central (Male) | Y62: No | Z62: 0 | AA62: On Zero % | AB62: +923181889545 | AC62: 7140268602293 | AD62: 38336 | AE62: Central (Rawalpindi / Lahore / Interior Punjab / Peshawar / etc) | AF62: Rawalpindi_Central Region | AG62: Rawalpindi jk | AH62: Male | AI62: Single | AJ62: Student | AK62: Below 25,000 | AL62: Support My Family members for Upskilling | AM62: 18-25 | AN62: FSc
A63: 1 | B63: 0 | C63: 1 | D63: 1 | E63: basitnuml2018@gmail.comGoogle Cybersecurity | F63: 62 | G63: Basit Ali | H63: basitnuml2018@gmail.com | I63: 1520293618411 | J63: Google Cybersecurity | K63: google-cybersecurity | L63: Google | M63: 2025-07-23T15:53:22.027Z | N63: 2025-11-01T15:33:41.240Z | O63: 3 | P63: 9 | Q63: No | R63: No | S63: akepb-central-male-qoy2h | T63: AKEPB - Central (Male) | V63: xCh7v | Y63: No | Z63: 0.33333333 | AA63: <40% | AB63: +923484624946 | AC63: 1520293618411 | AD63: 35757 | AE63: Central (Rawalpindi / Lahore / Interior Punjab / Peshawar / etc) | AF63: Rawalpindi_Central Region | AG63: Rawalpindi | AH63: Male | AI63: Single | AJ63: Employed | AK63: 60,000 - 80,000 | AL63: Advanced technical or soft skills training | AM63: 26-35 | AN63: Masters
A64: 0 | B64: 0 | D64: 0 | E64: maria.hunzai143@gmail.comGoogle IT Automation with Python | F64: 63 | G64: Maria Ali Hunzai | H64: maria.hunzai143@gmail.com | I64: 3520214485268 | J64: Google IT Automation with Python | K64: google-it-automation | L64: Google | M64: 2025-07-30T12:12:39.450Z | O64: 0 | P64: 7 | Q64: No | R64: No | S64: akepb-central-female-g5ddm | T64: AKEPB - Central (Female) | U64: Google Career Certificates Scholarship Program | V64: xCh7v | Y64: No | Z64: 0 | AA64: On Zero % | AB64: +923554364338 | AC64: 3520214485268 | AD64: 37931 | AE64: Central (Rawalpindi / Lahore / Interior Punjab / Peshawar / etc) | AF64: Rawalpindi_Central Region | AG64: Rawalpindi | AH64: Female | AI64: Single | AJ64: Student | AK64: 60,000 - 80,000 | AL64: Internship placements | AM64: 18-25 | AN64: FSc
A65: 1 | B65: 0 | C65: 1 | D65: 1 | E65: karishmaashrafbaig864@gmail.comGoogle Digital Marketing & E-commerce | F65: 64 | G65: Karishma Ashraf | H65: karishmaashrafbaig864@gmail.com | I65: 71401-3563061-2 | J65: Google Digital Marketing & E-commerce | K65: google-digital-marketing-ecommerce | L65: Google | M65: 2025-09-20T19:11:00.684Z | N65: 2025-10-23T12:58:11.502Z | O65: 2 | P65: 8 | Q65: No | R65: No | S65: akepb-central-male-qoy2h | T65: AKEPB - Central (Male) | V65: xCh7v | Y65: No | Z65: 0.25 | AA65: <30% | AB65: +923166982864 | AC65: 7140135630612 | AD65: 37688 | AE65: Gupis Yasin | AF65: Gupis_Gupis & Yasin Region | AG65: Rawalpindi JK | AH65: Female | AI65: Single | AJ65: Student | AK65: 25,000 - 50,000 | AL65: Job referrals or placement support | AM65: 18-25 | AN65: Bachelors
A66: 0 | B66: 0 | D66: 0 | E66: wasid.lums@gmail.comGoogle Data Analytics | F66: 65 | G66: Wasid Ahmed | H66: wasid.lums@gmail.com | I66: 7140303610483 | J66: Google Data Analytics | K66: google-data-analytics | L66: Google | M66: 2025-09-01T22:08:37.554Z | N66: 2025-10-07T00:48:09.470Z | O66: 0 | P66: 9 | Q66: No | R66: No | S66: akepb-central-male-qoy2h | T66: AKEPB - Central (Male) | U66: Google Career Certificates Scholarship Program | V66: xCh7v | Y66: No | Z66: 0 | AA66: On Zero % | AB66: +923465882856 | AC66: 7140303610483 | AD66: 37747 | AE66: Central (Rawalpindi / Lahore / Interior Punjab / Peshawar / etc) | AF66: Lahore_Central Region | AG66: Alflah Town JK Lahore | AH66: Male | AI66: Single | AJ66: Fresh Graduate | AK66: 25,000 - 50,000 | AL66: Advanced technical or soft skills training | AM66: 18-25 | AN66: Bachelors
A67: 0 | B67: 0 | D67: 0 | E67: nazeeraman93@gmail.comGoogle Data Analytics | F67: 66 | G67: Nazeer Aman | H67: nazeeraman93@gmail.com | I67: 7140253332139 | J67: Google Data Analytics | K67: google-data-analytics | L67: Google | M67: 2025-07-23T10:06:01.877Z | O67: 0 | P67: 9 | Q67: No | R67: No | S67: akepb-central-male-qoy2h | T67: AKEPB - Central (Male) | U67: Google Career Certificates Scholarship Program | Y67: No | Z67: 0 | AA67: On Zero % | AB67: +923170580327 | AC67: 7140253332139 | AD67: 36589 | AE67: Central (Rawalpindi / Lahore / Interior Punjab / Peshawar / etc) | AF67: Rawalpindi_Central Region | AG67: Ismaili Jamatkhanaa Chandi Chowk Rawalpindi | AH67: Male | AI67: Single | AJ67: Unemployed | AK67: 25,000 - 50,000 | AL67: Advanced technical or soft skills training | AM67: 18-25 | AN67: Bachelors
A68: 1 | B68: 0 | C68: 1 | D68: 1 | E68: baigshazoo@gmail.comGoogle Project Management | F68: 67 | G68: Shazmeena Baig | H68: baigshazoo@gmail.com | I68: 7150121713548 | J68: Google Project Management | K68: google-project-management | L68: Google | M68: 2025-07-23T13:46:59.206Z | N68: 2025-09-14T20:48:00.176Z | O68: 1 | P68: 7 | Q68: No | R68: No | S68: akepb-central-female-g5ddm | T68: AKEPB - Central (Female) | U68: Google Career Certificates Scholarship Program | Y68: No | Z68: 0.14285714 | AA68: <20% | AB68: +923422785678 | AC68: 7150121713548 | AD68: 37571 | AE68: Central (Rawalpindi / Lahore / Interior Punjab / Peshawar / etc) | AF68: Rawalpindi_Central Region | AG68: Karimabad Jamatkhana G9 | AH68: Female | AI68: Single | AJ68: Unemployed | AK68: 80,001 - 100,000 | AL68: Job referrals or placement support | AM68: 18-25 | AN68: Bachelors
A69: 1 | B69: 0 | C69: 1 | D69: 1 | E69: itsmehtabahmad@gmail.comGoogle Data Analytics | F69: 68 | G69: Mehtab Ahmad | H69: itsmehtabahmad@gmail.com | I69: 1520288898639 | J69: Google Data Analytics | K69: google-data-analytics | L69: Google | M69: 2025-07-25T10:00:14.737Z | N69: 2025-11-02T13:09:19.626Z | O69: 0 | P69: 9 | Q69: No | R69: No | S69: akepb-central-male-qoy2h | T69: AKEPB - Central (Male) | U69: Google Career Certificates Scholarship Program | Y69: No | Z69: 0 | AA69: On Zero % | AB69: +923463562864 | AC69: 1520288898639 | AD69: 37895 | AE69: Central (Rawalpindi / Lahore / Interior Punjab / Peshawar / etc) | AF69: Lahore_Central Region | AG69: Alfalah Town JK | AH69: Male | AI69: Single | AJ69: Student | AK69: Below 25,000 | AL69: Internship placements | AM69: 18-25 | AN69: Bachelors
A70: 0 | B70: 0 | D70: 0 | E70: irammurtaza732@gmail.comGoogle Business Intelligence | F70: 69 | G70: Iram Aliya | H70: irammurtaza732@gmail.com | I70: 7140290580446 | J70: Google Business Intelligence | K70: google-business-intelligence | L70: Google | M70: 2025-07-27T14:18:17.293Z | N70: 2025-08-12T18:34:52.586Z | O70: 0 | P70: 4 | Q70: No | R70: No | S70: akepb-central-female-g5ddm | T70: AKEPB - Central (Female) | U70: Google Career Certificates Scholarship Program | V70: GgvHw | Y70: No | Z70: 0 | AA70: On Zero % | AB70: +923477767164 | AC70: 7140290580446 | AD70: 36618 | AE70: Central (Rawalpindi / Lahore / Interior Punjab / Peshawar / etc) | AF70: Rawalpindi_Central Region | AG70: Islamabad/ Rawalpindi | AH70: Female | AI70: Single | AJ70: Student | AK70: 60,000 - 80,000 | AL70: Entrepreneurship support and mentoring | AM70: 18-25 | AN70: FSc
A71: 1 | B71: 0 | C71: 1 | D71: 1 | E71: komalhussain015@gmail.comGoogle Digital Marketing & E-commerce | F71: 70 | G71: Komal Hussain | H71: komalhussain015@gmail.com | I71: 1520265259434 | J71: Google Digital Marketing & E-commerce | K71: google-digital-marketing-ecommerce | L71: Google | M71: 2025-10-17T19:18:01.842Z | N71: 2025-10-17T19:19:48.975Z | O71: 0 | P71: 8 | Q71: No | R71: No | S71: akepb-central-female-g5ddm | T71: AKEPB - Central (Female) | V71: xCh7v | Y71: No | Z71: 0 | AA71: On Zero % | AB71: +923417369893 | AC71: 1520265259434 | AD71: 37026 | AE71: Central (Rawalpindi / Lahore / Interior Punjab / Peshawar / etc) | AF71: Rawalpindi_Central Region | AG71: Chandi chowk jk | AH71: Female | AI71: Single | AJ71: Student | AK71: 80,001 - 100,000 | AL71: Job referrals or placement support | AM71: 18-25 | AN71: Bachelors
A72: 0 | B72: 0 | D72: 0 | E72: neakparveen4@gmail.comGoogle Advanced Data Analytics | F72: 71 | G72: Neak parveen | H72: neakparveen4@gmail.com | I72: 6110152328138 | J72: Google Advanced Data Analytics | K72: google-advanced-data-analytics | L72: Google | M72: 2025-09-18T05:57:38.287Z | O72: 0 | P72: 8 | Q72: No | R72: No | S72: akepb-central-female-g5ddm | T72: AKEPB - Central (Female) | V72: xCh7v | Y72: No | Z72: 0 | AA72: On Zero % | AB72: +923402473122 | AC72: 6110152328138 | AD72: 35510 | AE72: Central (Rawalpindi / Lahore / Interior Punjab / Peshawar / etc) | AF72: Rawalpindi_Central Region | AG72: Rawalpindi | AH72: Female | AI72: Single | AJ72: Unemployed | AK72: 80,001 - 100,000 | AL72: Internship placements | AM72: 26-35 | AN72: Masters
A73: 0 | B73: 0 | D73: 0 | E73: nazeeraman93@gmail.comGoogle Prompting Essentials | F73: 72 | G73: Nazeer Aman | H73: nazeeraman93@gmail.com | I73: 7140253332139 | J73: Google Prompting Essentials | K73: prompting-essentials-google | L73: Google | M73: 2025-07-23T10:07:21.087Z | O73: 0 | P73: 4 | Q73: No | R73: No | S73: akepb-central-male-qoy2h | T73: AKEPB - Central (Male) | U73: Google Career Certificates Scholarship Program | Y73: No | Z73: 0 | AA73: On Zero % | AB73: +923170580327 | AC73: 7140253332139 | AD73: 36589 | AE73: Central (Rawalpindi / Lahore / Interior Punjab / Peshawar / etc) | AF73: Rawalpindi_Central Region | AG73: Ismaili Jamatkhanaa Chandi Chowk Rawalpindi | AH73: Male | AI73: Single | AJ73: Unemployed | AK73: 25,000 - 50,000 | AL73: Advanced technical or soft skills training | AM73: 18-25 | AN73: Bachelors
A74: 0 | B74: 0 | D74: 0 | E74: ghazanfar.shahgzr@gmail.comGoogle AI Essentials | F74: 73 | G74: Bibi Aftab | H74: ghazanfar.shahgzr@gmail.com | I74: 7140405765672 | J74: Google AI Essentials | K74: ai-essentials-google | L74: Google | M74: 2025-09-29T09:48:47.481Z | N74: 2025-10-26T18:40:05.237Z | O74: 4 | P74: 5 | Q74: No | R74: No | S74: akepb-central-female-g5ddm | T74: AKEPB - Central (Female) | Y74: No | Z74: 0.8 | AA74: <85% | AB74: +923169199644 | AC74: 7140405765672 | AD74: 39990 | AE74: Central (Rawalpindi / Lahore / Interior Punjab / Peshawar / etc) | AF74: Rawalpindi_Central Region | AG74: Rawalpindi | AH74: Female | AI74: Single | AJ74: Student | AK74: 25,000 - 50,000 | AL74: Advanced technical or soft skills training | AM74: 18-25 | AN74: Bachelors
A75: 1 | B75: 0 | C75: 1 | D75: 1 | E75: naeem.mubarak@ubas.edu.pkGoogle Project Management | F75: 74 | G75: Naeem Mubarak | H75: naeem.mubarak@ubas.edu.pk | I75: 3840215342341 | J75: Google Project Management | K75: google-project-management | L75: Google | M75: 2025-07-23T18:27:32.789Z | N75: 2025-09-14T11:07:25.735Z | O75: 2 | P75: 7 | Q75: No | R75: No | S75: akepb-central-male-qoy2h | T75: AKEPB - Central (Male) | Y75: No | Z75: 0.28571429 | AA75: <30% | AB75: +923335553729 | AC75: 3840215342341 | AD75: 30385 | AE75: Central (Rawalpindi / Lahore / Interior Punjab / Peshawar / etc) | AF75: Lahore_Central Region | AG75: Lahore | AH75: Male | AI75: Married | AJ75: Employed | AK75: 180,000 - 200,000 | AL75: Advanced technical or soft skills training | AM75: 36-45 | AN75: PhD
A76: 0 | B76: 0 | D76: 0 | E76: phenixflames0@gmail.comGoogle Advanced Data Analytics | F76: 75 | G76: Ali | H76: phenixflames0@gmail.com | I76: 3450137526777 | J76: Google Advanced Data Analytics | K76: google-advanced-data-analytics | L76: Google | M76: 2025-10-10T16:37:03.856Z | O76: 0 | P76: 8 | Q76: No | R76: No | S76: akepb-central-male-qoy2h | T76: AKEPB - Central (Male) | U76: Google Career Certificates Scholarship Program | V76: GgvHw | Y76: No | Z76: 0 | AA76: On Zero % | AB76: +923291794393 | AC76: 3450137526777 | AD76: 38578 | AE76: Central (Rawalpindi / Lahore / Interior Punjab / Peshawar / etc) | AF76: Lahore_Central Region | AG76: Shahdara | AH76: Male | AI76: Single | AJ76: Student | AK76: 25,000 - 50,000 | AL76: Advanced technical or soft skills training | AM76: 18-25 | AN76: FSc
A77: 0 | B77: 0 | D77: 0 | E77: rabikahussain9@gmail.comGoogle IT Automation with Python | F77: 76 | G77: Rabika Hussain | H77: rabikahussain9@gmail.com | I77: 1520189664078 | J77: Google IT Automation with Python | K77: google-it-automation | L77: Google | M77: 2025-07-23T10:10:37.256Z | N77: 2025-10-20T19:46:53.425Z | O77: 0 | P77: 7 | Q77: No | R77: No | S77: akepb-central-female-g5ddm | T77: AKEPB - Central (Female) | U77: Google Career Certificates Scholarship Program | V77: xCh7v | Y77: No | Z77: 0 | AA77: On Zero % | AB77: +923466586680 | AC77: 1520189664078 | AD77: 36970 | AE77: Central (Rawalpindi / Lahore / Interior Punjab / Peshawar / etc) | AF77: Rawalpindi_Central Region | AG77: Rawalpindi | AH77: Female | AI77: Single | AJ77: Unemployed | AK77: 60,000 - 80,000 | AL77: I learned about this scholarship opportunity from a friend who completed the same program. Seeing how it helped them gain valuable skills inspired me to apply, as I recognized how perfectly it aligns with my academic goals in Mathematics. | AM77: 18-25 | AN77: Bachelors
A78: 1 | B78: 0 | C78: 1 | D78: 1 | E78: gnasreen11@gmail.comGoogle AI Essentials | F78: 77 | G78: Gul Nasreen | H78: gnasreen11@gmail.com | I78: 1730157964176 | J78: Google AI Essentials | K78: ai-essentials-google | L78: Google | M78: 2025-08-05T11:36:16.446Z | N78: 2025-10-03T10:11:49.017Z | O78: 0 | P78: 5 | Q78: No | R78: No | S78: akepb-central-female-g5ddm | T78: AKEPB - Central (Female) | U78: Google Career Certificates Scholarship Program | Y78: No | Z78: 0 | AA78: On Zero % | AB78: +923339267482 | AC78: 1730157964176 | AD78: 31939 | AE78: Central (Rawalpindi / Lahore / Interior Punjab / Peshawar / etc) | AF78: Peshawar_Central Region | AG78: Peshawar | AH78: Female | AI78: Married | AJ78: Unemployed | AK78: 60,000 - 80,000 | AL78: Support My Family members for Upskilling | AM78: 36-45 | AN78: Masters
A79: 0 | B79: 0 | D79: 0 | E79: sohailak003@gmail.comGoogle UX Design | F79: 78 | G79: Sohail Ahmad Khan | H79: sohailak003@gmail.com | I79: 1520171241085 | J79: Google UX Design | K79: google-ux-design | L79: Google | M79: 2025-08-15T19:58:59.192Z | O79: 0 | P79: 8 | Q79: No | R79: No | S79: akepb-central-male-qoy2h | T79: AKEPB - Central (Male) | U79: Google Career Certificates Scholarship Program | V79: xCh7v | Y79: No | Z79: 0 | AA79: On Zero % | AB79: +923429188467 | AC79: 1520171241085 | AD79: 37710 | AE79: Central (Rawalpindi / Lahore / Interior Punjab / Peshawar / etc) | AF79: Peshawar_Central Region | AG79: Sikandar Town JK, Peshawar | AH79: Male | AI79: Single | AJ79: Student | AK79: 60,000 - 80,000 | AL79: Entrepreneurship support and mentoring | AM79: 18-25 | AN79: FSc
A80: 0 | B80: 0 | D80: 0 | E80: sherozeambreen@gmail.comGoogle Project Management | F80: 79 | G80: sharoze ambreen | H80: sherozeambreen@gmail.com | I80: 7170305670482 | J80: Google Project Management | K80: google-project-management | L80: Google | M80: 2025-08-10T15:34:17.648Z | N80: 2025-09-16T15:00:59.462Z | O80: 1 | P80: 7 | Q80: No | R80: No | S80: akepb-central-female-g5ddm | T80: AKEPB - Central (Female) | V80: xCh7v | Y80: No | Z80: 0.14285714 | AA80: <20% | AB80: +923463754093 | AC80: 7170305670482 | AD80: 36783 | AE80: Central (Rawalpindi / Lahore / Interior Punjab / Peshawar / etc) | AF80: Lahore_Central Region | AG80: Lahore jk | AH80: Female | AI80: Single | AJ80: Unemployed | AK80: 80,001 - 100,000 | AL80: Support My Family members for Upskilling | AM80: 18-25 | AN80: Bachelors
A81: 1 | B81: 0 | C81: 1 | D81: 1 | E81: aymensingal@gmail.comGoogle UX Design | F81: 80 | G81: Aiman Ali | H81: aymensingal@gmail.com | I81: 7140242920054 | J81: Google UX Design | K81: google-ux-design | L81: Google | M81: 2025-08-29T16:25:28.594Z | N81: 2025-09-23T20:00:12.957Z | O81: 0 | P81: 8 | Q81: No | R81: No | S81: akepb-central-female-g5ddm | T81: AKEPB - Central (Female) | U81: Google Career Certificates Scholarship Program | Y81: No | Z81: 0 | AA81: On Zero % | AB81: +923495182922 | AC81: 7140242920054 | AD81: 39429 | AE81: Central (Rawalpindi / Lahore / Interior Punjab / Peshawar / etc) | AF81: Rawalpindi_Central Region | AG81: Karimabad | AH81: Female | AI81: Single | AJ81: Student | AK81: Below 25,000 | AL81: Support My Family members for Upskilling | AM81: 18-25 | AN81: FSc
A82: 1 | B82: 0 | C82: 1 | D82: 1 | E82: asifwali049@gmail.comGoogle AI Essentials | F82: 81 | G82: Asif wali | H82: asifwali049@gmail.com | I82: 7140133169011 | J82: Google AI Essentials | K82: ai-essentials-google | L82: Google | M82: 2025-07-23T17:48:33.034Z | N82: 2025-08-11T11:41:28.680Z | O82: 2 | P82: 5 | Q82: No | R82: No | S82: akepb-central-male-qoy2h | T82: AKEPB - Central (Male) | U82: Google Career Certificates Scholarship Program | Y82: No | Z82: 0.4 | AA82: <40% | AB82: +923165733049 | AC82: 7140133169011 | AD82: 36892 | AE82: Central (Rawalpindi / Lahore / Interior Punjab / Peshawar / etc) | AF82: Rawalpindi_Central Region | AG82: Rawalpindi | AH82: Male | AI82: Single | AJ82: Unemployed | AK82: 25,000 - 50,000 | AL82: Entrepreneurship support and mentoring | AM82: 18-25 | AN82: Bachelors
A83: 1 | B83: 0 | C83: 1 | D83: 1 | E83: aiiman7475@gmail.comGoogle Data Analytics | F83: 82 | G83: Aiman Hanif | H83: aiiman7475@gmail.com | I83: 1730142513494 | J83: Google Data Analytics | K83: google-data-analytics | L83: Google | M83: 2025-07-27T10:34:51.088Z | O83: 0 | P83: 9 | Q83: No | R83: No | S83: akepb-central-female-g5ddm | T83: AKEPB - Central (Female) | U83: Google Career Certificates Scholarship Program | V83: xCh7v | Y83: No | Z83: 0 | AA83: On Zero % | AB83: +923174306871 | AC83: 1730142513494 | AD83: 35636 | AE83: Central (Rawalpindi / Lahore / Interior Punjab / Peshawar / etc) | AF83: Peshawar_Central Region | AG83: Amin Calony jamat khana | AH83: Female | AI83: Single | AJ83: Student | AK83: 25,000 - 50,000 | AL83: Participation in hackathons and innovation challenges | AM83: 26-35 | AN83: FSc
A84: 1 | B84: 0 | C84: 1 | D84: 1 | E84: tayyabaurooj.qau@gmail.comGoogle Project Management | F84: 83 | G84: Tayyaba Urooj | H84: tayyabaurooj.qau@gmail.com | I84: 3740537850676 | J84: Google Project Management | K84: google-project-management | L84: Google | M84: 2025-07-27T10:43:30.709Z | N84: 2025-10-21T07:13:39.000Z | O84: 1 | P84: 7 | Q84: No | R84: No | S84: akepb-central-female-g5ddm | T84: AKEPB - Central (Female) | U84: Google Career Certificates Scholarship Program | V84: GgvHw | Y84: No | Z84: 0.14285714 | AA84: <20% | AB84: +923198468960 | AC84: 3740537850676 | AD84: 37648 | AE84: Central (Rawalpindi / Lahore / Interior Punjab / Peshawar / etc) | AF84: Rawalpindi_Central Region | AG84: Chandni Chowk Rawalpindi | AH84: Female | AI84: Single | AJ84: Student | AK84: 80,001 - 100,000 | AL84: Job referrals or placement support | AM84: 18-25 | AN84: FSc
A85: 1 | B85: 0 | C85: 1 | D85: 1 | E85: alinazkiu@gmail.comGoogle Data Analytics | F85: 84 | G85: Ali Naz | H85: alinazkiu@gmail.com | I85: 7150124058800 | J85: Google Data Analytics | K85: google-data-analytics | L85: Google | M85: 2023-02-13T07:31:53.768Z | N85: 2025-10-20T09:41:15.951Z | O85: 1 | P85: 9 | Q85: No | R85: No | S85: akepb-gilgit-female-1kkb4 | T85: AKEPB - Gilgit II (Female) | U85: Google Career Certificates Scholarship Program | V85: xCh7v | Y85: No | Z85: 0.11111111 | AA85: <20% | AB85: +923129780735 | AC85: 7150124058800 | AD85: 32266 | AE85: Gilgit | AF85: Gilgit_Gilgit Region | AG85: Mujahid colony konodass Gilgit | AH85: Female | AI85: Single | AJ85: Employed | AK85: 180,000 - 200,000 | AL85: Advanced technical or soft skills training | AM85: 36-45 | AN85: Masters
A86: 1 | B86: 0 | C86: 1 | D86: 1 | E86: ptvamjadali@gmail.comGoogle AI Essentials | F86: 85 | G86: Amjad ali khan | H86: ptvamjadali@gmail.com | I86: 1520218481919 | J86: Google AI Essentials | K86: ai-essentials-google | L86: Google | M86: 2025-08-29T12:28:14.456Z | N86: 2025-10-24T06:59:49.353Z | O86: 0 | P86: 5 | Q86: No | R86: No | S86: akepb-central-male-qoy2h | T86: AKEPB - Central (Male) | Y86: No | Z86: 0 | AA86: On Zero % | AB86: +923448979957 | AC86: 1520218481919 | AD86: 33683 | AE86: Central (Rawalpindi / Lahore / Interior Punjab / Peshawar / etc) | AF86: Peshawar_Central Region | AG86: Sikandar Town Jamatkhana | AH86: Male | AI86: Married | AJ86: Employed | AK86: 100,001 - 120,000 | AL86: Advanced technical or soft skills training | AM86: 26-35 | AN86: Masters
A87: 1 | B87: 0 | C87: 1 | D87: 1 | E87: nabi.imran05@outlook.comGoogle Project Management | F87: 86 | G87: IMRAN NABI | H87: nabi.imran05@outlook.com | I87: 7150196332313 | J87: Google Project Management | K87: google-project-management | L87: Google | M87: 2025-07-29T11:27:09.715Z | N87: 2025-09-06T17:56:40.838Z | O87: 1 | P87: 7 | Q87: No | R87: No | S87: akepb-gilgit-male-gxr0q | T87: AKEPB - Gilgit II (Male) | U87: Google Career Certificates Scholarship Program | Y87: No | Z87: 0.14285714 | AA87: <20% | AB87: +923110593358 | AC87: 7150196332313 | AD87: 35872 | AE87: Gilgit | AF87: Gilgit_Gilgit Region | AG87: Central Jamat Khana Gilgit | AH87: Male | AI87: Married | AJ87: Employed | AK87: 80,001 - 100,000 | AL87: Support My Family members for Upskilling | AM87: 26-35 | AN87: Bachelors
A88: 1 | B88: 0 | C88: 1 | D88: 1 | E88: sher.arab12@gmail.comGoogle Data Analytics | F88: 87 | G88: Sher Arab | H88: sher.arab12@gmail.com | I88: 1520244554015 | J88: Google Data Analytics | K88: google-data-analytics | L88: Google | M88: 2025-07-24T04:41:44.518Z | N88: 2025-10-30T10:00:28.099Z | O88: 6 | P88: 9 | Q88: No | R88: No | S88: akepb-central-male-qoy2h | T88: AKEPB - Central (Male) | U88: Google Career Certificates Scholarship Program | Y88: No | Z88: 0.66666667 | AA88: <75% | AB88: +923488278790 | AC88: 1520244554015 | AD88: 33482 | AE88: Central (Rawalpindi / Lahore / Interior Punjab / Peshawar / etc) | AF88: Rawalpindi_Central Region | AG88: Islamabad | AH88: Male | AI88: Married | AJ88: Employed | AK88: 25,000 - 50,000 | AL88: Job referrals or placement support | AM88: 26-35 | AN88: Bachelors
A89: 0 | B89: 1 | D89: 0 | E89: ahmeduji247@gmail.comGoogle Data Analytics | F89: 88 | G89: Ujala Ahmed | H89: ahmeduji247@gmail.com | I89: 7150111187966 | J89: Google Data Analytics | K89: google-data-analytics | L89: Google | M89: 2023-04-04T12:23:28.331Z | N89: 2025-08-06T18:16:28.974Z | O89: 0 | P89: 9 | Q89: No | R89: No | S89: akepb-central-female-g5ddm | T89: AKEPB - Central (Female) | V89: GgvHw | Y89: No | Z89: 0 | AA89: On Zero % | AB89: +923151886629 | AC89: 7150111187966 | AD89: 37981 | AE89: Central (Rawalpindi / Lahore / Interior Punjab / Peshawar / etc) | AF89: Rawalpindi_Central Region | AG89: Karimabad jamat khana | AH89: Female | AI89: Single | AJ89: Student | AK89: 140,000 - 160,000 | AL89: Advanced technical or soft skills training | AM89: 18-25 | AN89: FSc
A90: 0 | B90: 1 | D90: 0 | E90: nisarfaiz560@gmail.comGoogle Project Management | F90: 89 | G90: Nisar Ahmad Faiz | H90: nisarfaiz560@gmail.com | I90: 1520163431333 | J90: Google Project Management | K90: google-project-management | L90: Google | M90: 2025-10-03T09:08:06.650Z | N90: 2025-10-18T07:35:29.079Z | O90: 0 | P90: 7 | Q90: No | R90: No | S90: akepb-central-male-qoy2h | T90: AKEPB - Central (Male) | U90: Google Career Certificates Scholarship Program | V90: GgvHw | Y90: No | Z90: 0 | AA90: On Zero % | AB90: +923498799983 | AC90: 1520163431333 | AD90: 38382 | AE90: Central (Rawalpindi / Lahore / Interior Punjab / Peshawar / etc) | AF90: Peshawar_Central Region | AG90: Sikandar town, Amin colony | AH90: Male | AI90: Single | AJ90: Student | AK90: 25,000 - 50,000 | AL90: Job referrals or placement support | AM90: 18-25 | AN90: FSc
A91: 0 | B91: 1 | D91: 0 | E91: wajeehatuzzahra30@gmail.comGoogle Data Analytics | F91: 90 | G91: Wajeeha Tuz Zahra | H91: wajeehatuzzahra30@gmail.com | I91: 1520165797960 | J91: Google Data Analytics | K91: google-data-analytics | L91: Google | M91: 2025-10-13T12:46:40.195Z | N91: 2025-10-13T13:46:55.386Z | O91: 1 | P91: 9 | Q91: No | R91: No | S91: akepb-central-female-g5ddm | T91: AKEPB - Central (Female) | V91: xCh7v | Y91: No | Z91: 0.11111111 | AA91: <20% | AB91: +923418725676 | AC91: 1520165797960 | AD91: 38959 | AE91: Central (Rawalpindi / Lahore / Interior Punjab / Peshawar / etc) | AF91: Rawalpindi_Central Region | AG91: G9 Jk | AH91: Female | AI91: Single | AJ91: Student | AK91: 140,000 - 160,000 | AL91: Advanced technical or soft skills training | AM91: 18-25 | AN91: FSc
A92: 0 | B92: 1 | D92: 0 | E92: rahilazafar130@gmail.comGoogle Data Analytics | F92: 91 | G92: Rahila Zafar | H92: rahilazafar130@gmail.com | I92: 7170205670826 | J92: Google Data Analytics | K92: google-data-analytics | L92: Google | M92: 2025-08-23T07:44:14.695Z | N92: 2025-08-23T11:49:58.736Z | O92: 0 | P92: 9 | Q92: No | R92: No | S92: akepb-central-female-g5ddm | T92: AKEPB - Central (Female) | V92: xCh7v | Y92: No | Z92: 0 | AA92: On Zero % | AB92: +923425536811 | AC92: 7170205670826 | AD92: 38080 | AE92: Central (Rawalpindi / Lahore / Interior Punjab / Peshawar / etc) | AF92: Rawalpindi_Central Region | AG92: Rawalpindi | AH92: Female | AI92: Single | AJ92: Student | AK92: 80,001 - 100,000 | AL92: Advanced technical or soft skills training | AM92: 18-25 | AN92: Bachelors
A93: 1 | B93: 0 | C93: 1 | D93: 1 | E93: karimzeeshan421@gmail.comGoogle Project Management | F93: 92 | G93: Zeeshan Karim | H93: karimzeeshan421@gmail.com | I93: 7150277192227 | J93: Google Project Management | K93: google-project-management | L93: Google | M93: 2025-10-03T15:51:21.848Z | N93: 2025-10-06T14:33:21.906Z | O93: 0 | P93: 7 | Q93: No | R93: No | S93: akepb-central-male-qoy2h | T93: AKEPB - Central (Male) | U93: Google Career Certificates Scholarship Program | V93: xCh7v | Y93: No | Z93: 0 | AA93: On Zero % | AB93: +923425192501 | AC93: 7150277192227 | AD93: 37585 | AE93: Central (Rawalpindi / Lahore / Interior Punjab / Peshawar / etc) | AF93: Lahore_Central Region | AG93: Alfalah town | AH93: Male | AI93: Single | AJ93: Student | AK93: 80,001 - 100,000 | AL93: Internship placements | AM93: 18-25 | AN93: Bachelors
A94: 0 | B94: 0 | D94: 0 | E94: sadiqullahshehzad941@gmail.comGoogle Project Management | F94: 93 | G94: Sadiq Ullah | H94: sadiqullahshehzad941@gmail.com | I94: 1520123108997 | J94: Google Project Management | K94: google-project-management | L94: Google | M94: 2021-04-14T06:43:49.838Z | O94: 0 | P94: 7 | Q94: No | R94: No | S94: akepb-central-male-qoy2h | T94: AKEPB - Central (Male) | U94: Google Career Certificates Scholarship Program | V94: xCh7v | Y94: No | Z94: 0 | AA94: On Zero % | AB94: +923340510521 | AC94: 1520123108997 | AD94: 36661 | AE94: Central (Rawalpindi / Lahore / Interior Punjab / Peshawar / etc) | AF94: Rawalpindi_Central Region | AG94: JK Karimabad G-9 | AH94: Male | AI94: Single | AJ94: Unemployed | AK94: 100,001 - 120,000 | AL94: Advanced technical or soft skills training | AM94: 18-25 | AN94: Bachelors
A95: 0 | B95: 0 | D95: 0 | E95: niaziruby23@gmail.comGoogle Data Analytics | F95: 94 | G95: Ruby Niazi | H95: niaziruby23@gmail.com | I95: 7150186768280 | J95: Google Data Analytics | K95: google-data-analytics | L95: Google | M95: 2025-07-29T07:26:12.520Z | N95: 2025-09-04T07:54:45.661Z | O95: 0 | P95: 9 | Q95: No | R95: No | S95: akepb-central-female-g5ddm | T95: AKEPB - Central (Female) | U95: Google Career Certificates Scholarship Program | V95: GgvHw | Y95: No | Z95: 0 | AA95: On Zero % | AB95: +923455054280 | AC95: 7150186768280 | AD95: 36312 | AE95: Central (Rawalpindi / Lahore / Interior Punjab / Peshawar / etc) | AF95: Lahore_Central Region | AG95: Lahore | AH95: Female | AI95: Single | AJ95: Employed | AK95: 140,000 - 160,000 | AL95: Support My Family members for Upskilling | AM95: 18-25 | AN95: Masters
A96: 0 | B96: 0 | D96: 0 | E96: shumailahameer0007@gmail.comGoogle UX Design | F96: 95 | G96: Shumailah Amir | H96: shumailahameer0007@gmail.com | I96: 7150197356394 | J96: Google UX Design | K96: google-ux-design | L96: Google | M96: 2025-09-08T09:50:25.990Z | N96: 2025-09-08T12:04:48.872Z | O96: 0 | P96: 8 | Q96: No | R96: No | S96: akepb-central-female-g5ddm | T96: AKEPB - Central (Female) | U96: Google Career Certificates Scholarship Program | Y96: No | Z96: 0 | AA96: On Zero % | AB96: +923478097639 | AC96: 7150197356394 | AD96: 37749 | AE96: Central (Rawalpindi / Lahore / Interior Punjab / Peshawar / etc) | AF96: Rawalpindi_Central Region | AG96: Rawalpindi | AH96: Female | AI96: Single | AJ96: Unemployed | AK96: 80,001 - 100,000 | AL96: Advanced technical or soft skills training | AM96: 18-25 | AN96: FSc
A97: 0 | B97: 1 | D97: 0 | E97: rukhsana.shah03@gmail.comGoogle Project Management | F97: 96 | G97: Rukhsana Shah | H97: rukhsana.shah03@gmail.com | I97: 7140295731118 | J97: Google Project Management | K97: google-project-management | L97: Google | M97: 2025-10-21T07:26:18.323Z | N97: 2025-10-22T06:09:54.763Z | O97: 1 | P97: 7 | Q97: No | R97: No | S97: akepb-central-female-g5ddm | T97: AKEPB - Central (Female) | V97: xCh7v | Y97: No | Z97: 0.14285714 | AA97: <20% | AB97: +923179469062 | AC97: 7140295731118 | AD97: 37721 | AE97: Central (Rawalpindi / Lahore / Interior Punjab / Peshawar / etc) | AF97: Rawalpindi_Central Region | AG97: Karimabad JK G9 | AH97: Female | AI97: Single | AJ97: Unemployed | AK97: 60,000 - 80,000 | AL97: Internship placements | AM97: 18-25 | AN97: Bachelors
A98: 1 | B98: 0 | C98: 1 | D98: 1 | E98: sabaveer41@gmail.comGoogle Data Analytics | F98: 97 | G98: Syeda sahiba kausar | H98: sabaveer41@gmail.com | I98: 1520257574672 | J98: Google Data Analytics | K98: google-data-analytics | L98: Google | M98: 2025-09-04T12:11:48.398Z | N98: 2025-09-04T12:12:33.008Z | O98: 0 | P98: 9 | Q98: No | R98: No | S98: akepb-central-female-g5ddm | T98: AKEPB - Central (Female) | V98: GgvHw | Y98: No | Z98: 0 | AA98: On Zero % | AB98: +923489399509 | AC98: 1520257574672 | AD98: 37335 | AE98: Central (Rawalpindi / Lahore / Interior Punjab / Peshawar / etc) | AF98: Peshawar_Central Region | AG98: Amin colony jk | AH98: Female | AI98: Single | AJ98: Fresh Graduate | AK98: 60,000 - 80,000 | AL98: Support My Family members for Upskilling | AM98: 18-25 | AN98: Bachelors
A99: 0 | B99: 0 | D99: 0 | E99: artas.kishwer@gmail.comGoogle Data Analytics | F99: 98 | G99: Kishwer Artas | H99: artas.kishwer@gmail.com | I99: 7140157837774 | J99: Google Data Analytics | K99: google-data-analytics | L99: Google | M99: 2025-09-05T09:42:51.453Z | N99: 2025-10-05T16:21:36.964Z | O99: 0 | P99: 9 | Q99: No | R99: No | S99: akepb-central-female-g5ddm | T99: AKEPB - Central (Female) | U99: Google Career Certificates Scholarship Program | V99: xCh7v | Y99: No | Z99: 0 | AA99: On Zero % | AB99: +923475407680 | AC99: 7140157837774 | AD99: 34716 | AE99: Central (Rawalpindi / Lahore / Interior Punjab / Peshawar / etc) | AF99: Rawalpindi_Central Region | AG99: Rawalpindi | AH99: Female | AI99: Single | AJ99: Unemployed | AK99: 100,001 - 120,000 | AL99: Advanced technical or soft skills training | AM99: 26-35 | AN99: Masters
A100: 1 | B100: 0 | C100: 1 | D100: 1 | E100: leenanaurozali20@gmail.comGoogle Cybersecurity | F100: 99 | G100: Leena Nauroz Ali | H100: leenanaurozali20@gmail.com | I100: 3430129575842 | J100: Google Cybersecurity | K100: google-cybersecurity | L100: Google | M100: 2025-07-23T13:18:13.806Z | N100: 2025-09-02T11:30:20.307Z | O100: 1 | P100: 9 | Q100: No | R100: No | S100: akepb-central-female-g5ddm | T100: AKEPB - Central (Female) | V100: xCh7v | Y100: No | Z100: 0.11111111 | AA100: <20% | AB100: +923350460205 | AC100: 3430129575842 | AD100: 39318 | AE100: Central (Rawalpindi / Lahore / Interior Punjab / Peshawar / etc) | AF100: Lahore_Central Region | AG100: Aga Khan road JK | AH100: Female | AI100: Single | AJ100: Student | AK100: 80,001 - 100,000 | AL100: Internship placements | AM100: 18-25 | AN100: FSc
...

Sheet National Dashboard
A1: GCC-Dashboard -(Pak Level) as of 5th Nov-2025
D5: Candidates Invited | H5: Candidates started any one course | L5: No. of Courses Registered | U5: Total Candidates not started any course
D7: =GETPIVOTDATA("Total Enrollment",'National Pivot'!$A$3) -> 1732 | H7: =+D7-U7 -> 1326 | L7: =GETPIVOTDATA("Sum of One verses Program Registered",'National Pivot'!$A$3) -> 2038 | U7: =GETPIVOTDATA("Unique Id",'National Pivot'!$H$4) -> 406
D8: M | E8: =GETPIVOTDATA("Sum of Count for Enrollment",'National Pivot'!$A$120,"Gender","Male") -> 918 | F8: =+E8/D7 -> 0.53002309 | H8: M | I8: =GETPIVOTDATA("Course Started",'National Pivot'!$A$120,"Gender","Male") -> 745 | J8: =I8/H7 -> 0.56184012 | U8: M | V8: =GETPIVOTDATA("Course Not started",'National Pivot'!$A$120,"Gender","Male") -> 173 | W8: =+V8/U7 -> 0.42610837
D9: F | E9: =GETPIVOTDATA("Sum of Count for Enrollment",'National Pivot'!$A$120,"Gender","Female") -> 700 | F9: =E9/D7 -> 0.40415704 | H9: F | I9: =GETPIVOTDATA("Course Started",'National Pivot'!$A$120,"Gender","Female") -> 548 | J9: =I9/H7 -> 0.413273 | U9: F | V9: =GETPIVOTDATA("Course Not started",'National Pivot'!$A$120,"Gender","Female") -> 152 | W9: =+V9/U7 -> 0.37438424
M27: No. of Candidates Completed 1 course | P27: Total no. of Course Completed
M29: =GETPIVOTDATA("Total Enrollment",'National Pivot'!$A$33) -> 247 | P29: =GETPIVOTDATA("Count of Count for Yes",'National Pivot'!$A$33) -> 341
C50: No. of Candidates | F50: Total no. of Course >50% Completion | L50: No. of Candidates | O50: Total no. of Course < 50% Completion | V50: No. of Candidates | Y50: Total no. of Course on 0% Completion
C52: =GETPIVOTDATA("Total Enrollment",'National Pivot'!$O$33) -> 78 | F52: =GETPIVOTDATA("Count of Specialization",'National Pivot'!$O$33) -> 119 | L52: =GETPIVOTDATA("Total Enrollment",'National Pivot'!$G$33) -> 396 | O52: =GETPIVOTDATA("Count of Specialization",'National Pivot'!$G$33) -> 622 | V52: =GETPIVOTDATA("Total Enrollment",'National Pivot'!$K$33) -> 605 | Y52: =GETPIVOTDATA("Count of Specialization",'National Pivot'!$K$33) -> 956

Sheet Region Wise Dashboard
A1: =CONCATENATE("GCC Dashboard for"," ",'Regions Pivot'!P1," as of 5th Nov 2025") -> GCC Dashboard for Southern (Karachi / Interior Sindh) as of 5th Nov 2025
F10: Candidates Invited | J10: Candidates started any one course | O10: No. of Courses Registered
F12: =GETPIVOTDATA("Sum of Count for Enrollment",'Regions Pivot'!$A$3) -> 585 | J12: =GETPIVOTDATA("Sum of Count for Candiodates started course",'Regions Pivot'!$A$3) -> 501 | O12: =GETPIVOTDATA("Count of Specialization",'Regions Pivot'!$A$3) -> 840
K31: Candidates not started Program
K33: =GETPIVOTDATA("Unique Id",'Regions Pivot'!$I$4) -> 84
I55: Candidates on 100% Completion | N55: No. of Courses Completed
I57: =GETPIVOTDATA("Candidates",'Regions Pivot'!$A$29) -> 134 | N57: =GETPIVOTDATA("Courses Completed",'Regions Pivot'!$A$29) -> 211
I75: Candidates on >50% Completion | N75: No. of Courses >50%
I77: =GETPIVOTDATA("Candidates",'Regions Pivot'!$E$29) -> 39 | N77: =GETPIVOTDATA("Courses Completed",'Regions Pivot'!$E$29) -> 61
I97: Candidates on <50% Completion | N97: No. of Courses <50%
I99: =GETPIVOTDATA("Candidates",'Regions Pivot'!$J$29) -> 129 | N99: =GETPIVOTDATA("Courses Completed",'Regions Pivot'!$J$29) -> 233
I119: Candidates on 0% Completion | N119: No. of Courses 0%
I121: =GETPIVOTDATA("Candidates",'Regions Pivot'!$P$29) -> 201 | N121: =GETPIVOTDATA("Courses Completed",'Regions Pivot'!$P$29) -> 337
